Workbook

Sheet T LIGHT HOLDER 
A1: Week_start | B1: 22423 REGENCY CAKESTAND 3 TI | C1: 85123A WHITE HANGING HEART T- | D1: 85099B JUMBO BAG RED RETROSPO | E1: 47566 PARTY BUNTING | F1: 84879 ASSORTED COLOUR BIRD O | G1: 22086 PAPER CHAIN KIT 50'S C | H1: 79321 CHILLI LIGHTS | I1: 22197 SMALL POPCORN HOLDER | J1: 22386 JUMBO BAG PINK POLKADO | K1: 20725 LUNCH BAG RED RETROSPO | L1: MA3_FORECAST | M1: ERROR | N1: ABS ERROR | O1: ES_0.1 | P1: ES_0.3 | Q1: ES_0.5 | R1: ALPHA | S1: 0.1 | V1: ABSERR_0.1 | W1: ABSERR_0.3 | X1: ABSERR_0.5
A2: 40154 | B2: 0 | C2: 3166 | D2: 1233 | E2: 19 | F2: 1213 | G2: 663 | H2: 175 | I2: 153 | J2: 0 | K2: 324 | O2: =(C2) -> 3166 | P2: =(C2) -> 3166 | Q2: =(C2) -> 3166 | S2: 0.3
A3: 40161 | B3: 0 | C3: 1294 | D3: 1304 | E3: 52 | F3: 1324 | G3: 572 | H3: 173 | I3: 644 | J3: 0 | K3: 236 | O3: =($S$1*C2+(1-$S$1)*O2) -> 3166 | P3: =($S$2*C2+(1-$S$2)*P2) -> 3166 | Q3: =($S$3*C2+(1-$S$3)*Q2) -> 3166 | S3: 0.5 | V3: =ABS(C3-O3) -> 1872 | W3: =ABS(C3-P3) -> 1872 | X3: =ABS(C3-Q3) -> 1872
A4: 40168 | B4: 0 | C4: 128 | D4: 36 | E4: 1 | F4: 82 | G4: 69 | H4: 19 | I4: 2 | J4: 0 | K4: 111 | O4: =($S$1*C3+(1-$S$1)*O3) -> 2978.8 | P4: =($S$2*C3+(1-$S$2)*P3) -> 2604.4 | Q4: =($S$3*C3+(1-$S$3)*Q3) -> 2230 | V4: =ABS(C4-O4) -> 2850.8 | W4: =ABS(C4-P4) -> 2476.4 | X4: =ABS(C4-Q4) -> 2102
A5: 40175 | B5: 0 | C5: 0 | D5: 0 | E5: 0 | F5: 0 | G5: 0 | H5: 0 | I5: 0 | J5: 0 | K5: 0 | L5: =AVERAGE(C2:C4) -> 1529.3333 | M5: =(C5-L5) -> -1529.3333 | N5: =ABS(M5) -> 1529.3333 | O5: =($S$1*C4+(1-$S$1)*O4) -> 2693.72 | P5: =($S$2*C4+(1-$S$2)*P4) -> 1861.48 | Q5: =($S$3*C4+(1-$S$3)*Q4) -> 1179 | V5: =ABS(C5-O5) -> 2693.72 | W5: =ABS(C5-P5) -> 1861.48 | X5: =ABS(C5-Q5) -> 1179
A6: 40182 | B6: 0 | C6: 1773 | D6: 1152 | E6: 47 | F6: 168 | G6: 0 | H6: 17 | I6: 21 | J6: 0 | K6: 324 | L6: =AVERAGE(C3:C5) -> 474 | M6: =(C6-L6) -> 1299 | N6: =ABS(M6) -> 1299 | O6: =($S$1*C5+(1-$S$1)*O5) -> 2424.348 | P6: =($S$2*C5+(1-$S$2)*P5) -> 1303.036 | Q6: =($S$3*C5+(1-$S$3)*Q5) -> 589.5 | V6: =ABS(C6-O6) -> 651.348 | W6: =ABS(C6-P6) -> 469.964 | X6: =ABS(C6-Q6) -> 1183.5
A7: 40189 | B7: 0 | C7: 920 | D7: 928 | E7: 64 | F7: 233 | G7: 20 | H7: 23 | I7: 72 | J7: 0 | K7: 190 | L7: =AVERAGE(C4:C6) -> 633.66667 | M7: =(C7-L7) -> 286.33333 | N7: =ABS(M7) -> 286.33333 | O7: =($S$1*C6+(1-$S$1)*O6) -> 2359.2132 | P7: =($S$2*C6+(1-$S$2)*P6) -> 1444.0252 | Q7: =($S$3*C6+(1-$S$3)*Q6) -> 1181.25 | V7: =ABS(C7-O7) -> 1439.2132 | W7: =ABS(C7-P7) -> 524.0252 | X7: =ABS(C7-Q7) -> 261.25
A8: 40196 | B8: 0 | C8: 1404 | D8: 627 | E8: 49 | F8: 897 | G8: 3 | H8: 0 | I8: 23 | J8: 0 | K8: 479 | L8: =AVERAGE(C5:C7) -> 897.66667 | M8: =(C8-L8) -> 506.33333 | N8: =ABS(M8) -> 506.33333 | O8: =($S$1*C7+(1-$S$1)*O7) -> 2215.2919 | P8: =($S$2*C7+(1-$S$2)*P7) -> 1286.8176 | Q8: =($S$3*C7+(1-$S$3)*Q7) -> 1050.625 | V8: =ABS(C8-O8) -> 811.29188 | W8: =ABS(C8-P8) -> 117.18236 | X8: =ABS(C8-Q8) -> 353.375
A9: 40203 | B9: 0 | C9: 1382 | D9: 864 | E9: 186 | F9: 211 | G9: 0 | H9: 0 | I9: 621 | J9: 114 | K9: 504 | L9: =AVERAGE(C6:C8) -> 1365.6667 | M9: =(C9-L9) -> 16.333333 | N9: =ABS(M9) -> 16.333333 | O9: =($S$1*C8+(1-$S$1)*O8) -> 2134.1627 | P9: =($S$2*C8+(1-$S$2)*P8) -> 1321.9723 | Q9: =($S$3*C8+(1-$S$3)*Q8) -> 1227.3125 | V9: =ABS(C9-O9) -> 752.16269 | W9: =ABS(C9-P9) -> 60.027652 | X9: =ABS(C9-Q9) -> 154.6875
A10: 40210 | B10: 0 | C10: 727 | D10: 488 | E10: 53 | F10: 274 | G10: 0 | H10: 24 | I10: 81 | J10: 338 | K10: 326 | L10: =AVERAGE(C7:C9) -> 1235.3333 | M10: =(C10-L10) -> -508.33333 | N10: =ABS(M10) -> 508.33333 | O10: =($S$1*C9+(1-$S$1)*O9) -> 2058.9464 | P10: =($S$2*C9+(1-$S$2)*P9) -> 1339.9806 | Q10: =($S$3*C9+(1-$S$3)*Q9) -> 1304.6562 | V10: =ABS(C10-O10) -> 1331.9464 | W10: =ABS(C10-P10) -> 612.98064 | X10: =ABS(C10-Q10) -> 577.65625
A11: 40217 | B11: 0 | C11: 580 | D11: 547 | E11: 51 | F11: 512 | G11: 0 | H11: 0 | I11: 68 | J11: 314 | K11: 213 | L11: =AVERAGE(C8:C10) -> 1171 | M11: =(C11-L11) -> -591 | N11: =ABS(M11) -> 591 | O11: =($S$1*C10+(1-$S$1)*O10) -> 1925.7518 | P11: =($S$2*C10+(1-$S$2)*P10) -> 1156.0865 | Q11: =($S$3*C10+(1-$S$3)*Q10) -> 1015.8281 | V11: =ABS(C11-O11) -> 1345.7518 | W11: =ABS(C11-P11) -> 576.08645 | X11: =ABS(C11-Q11) -> 435.82812
A12: 40224 | B12: 0 | C12: 669 | D12: 1014 | E12: 159 | F12: 587 | G12: 0 | H12: 1 | I12: 19 | J12: 720 | K12: 442 | L12: =AVERAGE(C9:C11) -> 896.33333 | M12: =(C12-L12) -> -227.33333 | N12: =ABS(M12) -> 227.33333 | O12: =($S$1*C11+(1-$S$1)*O11) -> 1791.1766 | P12: =($S$2*C11+(1-$S$2)*P11) -> 983.26052 | Q12: =($S$3*C11+(1-$S$3)*Q11) -> 797.91406 | V12: =ABS(C12-O12) -> 1122.1766 | W12: =ABS(C12-P12) -> 314.26052 | X12: =ABS(C12-Q12) -> 128.91406
A13: 40231 | B13: 0 | C13: 929 | D13: 613 | E13: 79 | F13: 294 | G13: 0 | H13: 0 | I13: 1407 | J13: 551 | K13: 272 | L13: =AVERAGE(C10:C12) -> 658.66667 | M13: =(C13-L13) -> 270.33333 | N13: =ABS(M13) -> 270.33333 | O13: =($S$1*C12+(1-$S$1)*O12) -> 1678.9589 | P13: =($S$2*C12+(1-$S$2)*P12) -> 888.98236 | Q13: =($S$3*C12+(1-$S$3)*Q12) -> 733.45703 | V13: =ABS(C13-O13) -> 749.95894 | W13: =ABS(C13-P13) -> 40.017639 | X13: =ABS(C13-Q13) -> 195.54297
A14: 40238 | B14: 0 | C14: 842 | D14: 754 | E14: 78 | F14: 735 | G14: 3 | H14: 2 | I14: 133 | J14: 306 | K14: 409 | L14: =AVERAGE(C11:C13) -> 726 | M14: =(C14-L14) -> 116 | N14: =ABS(M14) -> 116 | O14: =($S$1*C13+(1-$S$1)*O13) -> 1603.963 | P14: =($S$2*C13+(1-$S$2)*P13) -> 900.98765 | Q14: =($S$3*C13+(1-$S$3)*Q13) -> 831.22852 | V14: =ABS(C14-O14) -> 761.96305 | W14: =ABS(C14-P14) -> 58.987653 | X14: =ABS(C14-Q14) -> 10.771484
A15: 40245 | B15: 0 | C15: 848 | D15: 800 | E15: 262 | F15: 917 | G15: 0 | H15: 0 | I15: 47 | J15: 405 | K15: 337 | L15: =AVERAGE(C12:C14) -> 813.33333 | M15: =(C15-L15) -> 34.666667 | N15: =ABS(M15) -> 34.666667 | O15: =($S$1*C14+(1-$S$1)*O14) -> 1527.7667 | P15: =($S$2*C14+(1-$S$2)*P14) -> 883.29136 | Q15: =($S$3*C14+(1-$S$3)*Q14) -> 836.61426 | V15: =ABS(C15-O15) -> 679.76674 | W15: =ABS(C15-P15) -> 35.291357 | X15: =ABS(C15-Q15) -> 11.385742
A16: 40252 | B16: 194 | C16: 1496 | D16: 555 | E16: 224 | F16: 551 | G16: 12 | H16: 0 | I16: 826 | J16: 179 | K16: 375 | L16: =AVERAGE(C13:C15) -> 873 | M16: =(C16-L16) -> 623 | N16: =ABS(M16) -> 623 | O16: =($S$1*C15+(1-$S$1)*O15) -> 1459.7901 | P16: =($S$2*C15+(1-$S$2)*P15) -> 872.70395 | Q16: =($S$3*C15+(1-$S$3)*Q15) -> 842.30713 | V16: =ABS(C16-O16) -> 36.209931 | W16: =ABS(C16-P16) -> 623.29605 | X16: =ABS(C16-Q16) -> 653.69287
... A105: 40875 | B105: 226 | C105: 726 | D105: 1040 | E105: 105 | F105: 953 | G105: 1564 | H105: 314 | I105: 3275 | J105: 436 | K105: 331 | L105: =AVERAGE(C102:C104) -> 931.66667 | M105: =(C105-L105) -> -205.66667 | N105: =ABS(M105) -> 205.66667 | O105: =($S$1*C104+(1-$S$1)*O104) -> 713.99021 | P105: =($S$2*C104+(1-$S$2)*P104) -> 909.21415 | Q105: =($S$3*C104+(1-$S$3)*Q104) -> 983.26206 | V105: =ABS(C105-O105) -> 12.009791 | W105: =ABS(C105-P105) -> 183.21415 | X105: =ABS(C105-Q105) -> 257.26206
T106: MAD _M3 | U106: =AVERAGE(N94:N105) -> 322.88889
T107: MAD _ES_0.1 | U107: =AVERAGE(V94:V105) -> 292.34878
T108: MAD _ES_0.3 | U108: =AVERAGE(W94:W105) -> 310.91623
T109: MAD _ES_0.5 | U109: =AVERAGE(X94:X105) -> 360.64191
V111: AVERAGE | W111: STD DEV
V112: =AVERAGE(C2:C105) -> 850.56731 | W112: =STDEV(C2:C105) -> 496.45232

Sheet JUMBO BAG PINK
A1: Week_start | B1: 22423 REGENCY CAKESTAND 3 TI | C1: 85123A WHITE HANGING HEART T- | D1: 85099B JUMBO BAG RED RETROSPO | E1: 47566 PARTY BUNTING | F1: 84879 ASSORTED COLOUR BIRD O | G1: 22086 PAPER CHAIN KIT 50'S C | H1: 79321 CHILLI LIGHTS | I1: 22197 SMALL POPCORN HOLDER | J1: 22386 JUMBO BAG PINK POLKADO | K1: 20725 LUNCH BAG RED RETROSPO | L1: MA3_FORECAST | M1: ERROR | N1: ABS ERROR | O1: ES_0.1 | P1: ES_0.3 | Q1: ES_0.5 | R1: ALPHA | S1: 0.1 | V1: ABSERR_0.1 | W1: ABSERR_0.3 | X1: ABSERR_0.5
A2: 40154 | B2: 0 | C2: 0 | D2: 1233 | E2: 19 | F2: 1213 | G2: 663 | H2: 175 | I2: 153 | J2: 0 | K2: 324 | O2: =(C2) -> 0 | P2: =(C2) -> 0 | Q2: =(C2) -> 0 | S2: 0.3
A3: 40161 | B3: 0 | C3: 0 | D3: 1304 | E3: 52 | F3: 1324 | G3: 572 | H3: 173 | I3: 644 | J3: 0 | K3: 236 | O3: =($S$1*C2+(1-$S$1)*O2) -> 0 | P3: =($S$2*C2+(1-$S$2)*P2) -> 0 | Q3: =($S$3*C2+(1-$S$3)*Q2) -> 0 | S3: 0.5 | V3: =ABS(C3-O3) -> 0 | W3: =ABS(C3-P3) -> 0 | X3: =ABS(C3-Q3) -> 0
A4: 40168 | B4: 0 | C4: 0 | D4: 36 | E4: 1 | F4: 82 | G4: 69 | H4: 19 | I4: 2 | J4: 0 | K4: 111 | O4: =($S$1*C3+(1-$S$1)*O3) -> 0 | P4: =($S$2*C3+(1-$S$2)*P3) -> 0 | Q4: =($S$3*C3+(1-$S$3)*Q3) -> 0 | V4: =ABS(C4-O4) -> 0 | W4: =ABS(C4-P4) -> 0 | X4: =ABS(C4-Q4) -> 0
A5: 40175 | B5: 0 | C5: 0 | D5: 0 | E5: 0 | F5: 0 | G5: 0 | H5: 0 | I5: 0 | J5: 0 | K5: 0 | L5: =AVERAGE(C2:C4) -> 0 | M5: =(C5-L5) -> 0 | N5: =ABS(M5) -> 0 | O5: =($S$1*C4+(1-$S$1)*O4) -> 0 | P5: =($S$2*C4+(1-$S$2)*P4) -> 0 | Q5: =($S$3*C4+(1-$S$3)*Q4) -> 0 | V5: =ABS(C5-O5) -> 0 | W5: =ABS(C5-P5) -> 0 | X5: =ABS(C5-Q5) -> 0
A6: 40182 | B6: 0 | C6: 0 | D6: 1152 | E6: 47 | F6: 168 | G6: 0 | H6: 17 | I6: 21 | J6: 0 | K6: 324 | L6: =AVERAGE(C3:C5) -> 0 | M6: =(C6-L6) -> 0 | N6: =ABS(M6) -> 0 | O6: =($S$1*C5+(1-$S$1)*O5) -> 0 | P6: =($S$2*C5+(1-$S$2)*P5) -> 0 | Q6: =($S$3*C5+(1-$S$3)*Q5) -> 0 | V6: =ABS(C6-O6) -> 0 | W6: =ABS(C6-P6) -> 0 | X6: =ABS(C6-Q6) -> 0
A7: 40189 | B7: 0 | C7: 0 | D7: 928 | E7: 64 | F7: 233 | G7: 20 | H7: 23 | I7: 72 | J7: 0 | K7: 190 | L7: =AVERAGE(C4:C6) -> 0 | M7: =(C7-L7) -> 0 | N7: =ABS(M7) -> 0 | O7: =($S$1*C6+(1-$S$1)*O6) -> 0 | P7: =($S$2*C6+(1-$S$2)*P6) -> 0 | Q7: =($S$3*C6+(1-$S$3)*Q6) -> 0 | V7: =ABS(C7-O7) -> 0 | W7: =ABS(C7-P7) -> 0 | X7: =ABS(C7-Q7) -> 0
A8: 40196 | B8: 0 | C8: 0 | D8: 627 | E8: 49 | F8: 897 | G8: 3 | H8: 0 | I8: 23 | J8: 0 | K8: 479 | L8: =AVERAGE(C5:C7) -> 0 | M8: =(C8-L8) -> 0 | N8: =ABS(M8) -> 0 | O8: =($S$1*C7+(1-$S$1)*O7) -> 0 | P8: =($S$2*C7+(1-$S$2)*P7) -> 0 | Q8: =($S$3*C7+(1-$S$3)*Q7) -> 0 | V8: =ABS(C8-O8) -> 0 | W8: =ABS(C8-P8) -> 0 | X8: =ABS(C8-Q8) -> 0
A9: 40203 | B9: 0 | C9: 114 | D9: 864 | E9: 186 | F9: 211 | G9: 0 | H9: 0 | I9: 621 | J9: 114 | K9: 504 | L9: =AVERAGE(C6:C8) -> 0 | M9: =(C9-L9) -> 114 | N9: =ABS(M9) -> 114 | O9: =($S$1*C8+(1-$S$1)*O8) -> 0 | P9: =($S$2*C8+(1-$S$2)*P8) -> 0 | Q9: =($S$3*C8+(1-$S$3)*Q8) -> 0 | V9: =ABS(C9-O9) -> 114 | W9: =ABS(C9-P9) -> 114 | X9: =ABS(C9-Q9) -> 114
A10: 40210 | B10: 0 | C10: 338 | D10: 488 | E10: 53 | F10: 274 | G10: 0 | H10: 24 | I10: 81 | J10: 338 | K10: 326 | L10: =AVERAGE(C7:C9) -> 38 | M10: =(C10-L10) -> 300 | N10: =ABS(M10) -> 300 | O10: =($S$1*C9+(1-$S$1)*O9) -> 11.4 | P10: =($S$2*C9+(1-$S$2)*P9) -> 34.2 | Q10: =($S$3*C9+(1-$S$3)*Q9) -> 57 | V10: =ABS(C10-O10) -> 326.6 | W10: =ABS(C10-P10) -> 303.8 | X10: =ABS(C10-Q10) -> 281
A11: 40217 | B11: 0 | C11: 314 | D11: 547 | E11: 51 | F11: 512 | G11: 0 | H11: 0 | I11: 68 | J11: 314 | K11: 213 | L11: =AVERAGE(C8:C10) -> 150.66667 | M11: =(C11-L11) -> 163.33333 | N11: =ABS(M11) -> 163.33333 | O11: =($S$1*C10+(1-$S$1)*O10) -> 44.06 | P11: =($S$2*C10+(1-$S$2)*P10) -> 125.34 | Q11: =($S$3*C10+(1-$S$3)*Q10) -> 197.5 | V11: =ABS(C11-O11) -> 269.94 | W11: =ABS(C11-P11) -> 188.66 | X11: =ABS(C11-Q11) -> 116.5
A12: 40224 | B12: 0 | C12: 720 | D12: 1014 | E12: 159 | F12: 587 | G12: 0 | H12: 1 | I12: 19 | J12: 720 | K12: 442 | L12: =AVERAGE(C9:C11) -> 255.33333 | M12: =(C12-L12) -> 464.66667 | N12: =ABS(M12) -> 464.66667 | O12: =($S$1*C11+(1-$S$1)*O11) -> 71.054 | P12: =($S$2*C11+(1-$S$2)*P11) -> 181.938 | Q12: =($S$3*C11+(1-$S$3)*Q11) -> 255.75 | V12: =ABS(C12-O12) -> 648.946 | W12: =ABS(C12-P12) -> 538.062 | X12: =ABS(C12-Q12) -> 464.25
A13: 40231 | B13: 0 | C13: 551 | D13: 613 | E13: 79 | F13: 294 | G13: 0 | H13: 0 | I13: 1407 | J13: 551 | K13: 272 | L13: =AVERAGE(C10:C12) -> 457.33333 | M13: =(C13-L13) -> 93.666667 | N13: =ABS(M13) -> 93.666667 | O13: =($S$1*C12+(1-$S$1)*O12) -> 135.9486 | P13: =($S$2*C12+(1-$S$2)*P12) -> 343.3566 | Q13: =($S$3*C12+(1-$S$3)*Q12) -> 487.875 | V13: =ABS(C13-O13) -> 415.0514 | W13: =ABS(C13-P13) -> 207.6434 | X13: =ABS(C13-Q13) -> 63.125
A14: 40238 | B14: 0 | C14: 306 | D14: 754 | E14: 78 | F14: 735 | G14: 3 | H14: 2 | I14: 133 | J14: 306 | K14: 409 | L14: =AVERAGE(C11:C13) -> 528.33333 | M14: =(C14-L14) -> -222.33333 | N14: =ABS(M14) -> 222.33333 | O14: =($S$1*C13+(1-$S$1)*O13) -> 177.45374 | P14: =($S$2*C13+(1-$S$2)*P13) -> 405.64962 | Q14: =($S$3*C13+(1-$S$3)*Q13) -> 519.4375 | V14: =ABS(C14-O14) -> 128.54626 | W14: =ABS(C14-P14) -> 99.64962 | X14: =ABS(C14-Q14) -> 213.4375
A15: 40245 | B15: 0 | C15: 405 | D15: 800 | E15: 262 | F15: 917 | G15: 0 | H15: 0 | I15: 47 | J15: 405 | K15: 337 | L15: =AVERAGE(C12:C14) -> 525.66667 | M15: =(C15-L15) -> -120.66667 | N15: =ABS(M15) -> 120.66667 | O15: =($S$1*C14+(1-$S$1)*O14) -> 190.30837 | P15: =($S$2*C14+(1-$S$2)*P14) -> 375.75473 | Q15: =($S$3*C14+(1-$S$3)*Q14) -> 412.71875 | V15: =ABS(C15-O15) -> 214.69163 | W15: =ABS(C15-P15) -> 29.245266 | X15: =ABS(C15-Q15) -> 7.71875
A16: 40252 | B16: 194 | C16: 179 | D16: 555 | E16: 224 | F16: 551 | G16: 12 | H16: 0 | I16: 826 | J16: 179 | K16: 375 | L16: =AVERAGE(C13:C15) -> 420.66667 | M16: =(C16-L16) -> -241.66667 | N16: =ABS(M16) -> 241.66667 | O16: =($S$1*C15+(1-$S$1)*O15) -> 211.77753 | P16: =($S$2*C15+(1-$S$2)*P15) -> 384.52831 | Q16: =($S$3*C15+(1-$S$3)*Q15) -> 408.85938 | V16: =ABS(C16-O16) -> 32.777529 | W16: =ABS(C16-P16) -> 205.52831 | X16: =ABS(C16-Q16) -> 229.85938
... A105: 40875 | B105: 226 | C105: 436 | D105: 1040 | E105: 105 | F105: 953 | G105: 1564 | H105: 314 | I105: 3275 | J105: 436 | K105: 331 | L105: =AVERAGE(C102:C104) -> 397 | M105: =(C105-L105) -> 39 | N105: =ABS(M105) -> 39 | O105: =($S$1*C104+(1-$S$1)*O104) -> 496.35066 | P105: =($S$2*C104+(1-$S$2)*P104) -> 426.46233 | Q105: =($S$3*C104+(1-$S$3)*Q104) -> 364.75076 | V105: =ABS(C105-O105) -> 60.350662 | W105: =ABS(C105-P105) -> 9.5376724 | X105: =ABS(C105-Q105) -> 71.249245
T106: MAD _M3 | U106: =AVERAGE(N94:N105) -> 265.33333
T107: MAD _ES_0.1 | U107: =AVERAGE(V94:V105) -> 262.64284
T108: MAD _ES_0.3 | U108: =AVERAGE(W94:W105) -> 271.50823
T109: MAD _ES_0.5 | U109: =AVERAGE(X94:X105) -> 287.00668
V111: AVERAGE | W111: STD DEV
V112: =AVERAGE(C2:C105) -> 374.125 | W112: =STDEV(C2:C105) -> 254.29952

Sheet LUNCH BAG RED
A1: Week_start | B1: 22423 REGENCY CAKESTAND 3 TI | C1: 85123A WHITE HANGING HEART T- | D1: 85099B JUMBO BAG RED RETROSPO | E1: 47566 PARTY BUNTING | F1: 84879 ASSORTED COLOUR BIRD O | G1: 22086 PAPER CHAIN KIT 50'S C | H1: 79321 CHILLI LIGHTS | I1: 22197 SMALL POPCORN HOLDER | J1: 22386 JUMBO BAG PINK POLKADO | K1: 20725 LUNCH BAG RED RETROSPO | L1: MA3_FORECAST | M1: ERROR | N1: ABS ERROR | O1: ES_0.1 | P1: ES_0.3 | Q1: ES_0.5 | R1: ALPHA | S1: 0.1 | V1: ABSERR_0.1 | W1: ABSERR_0.3 | X1: ABSERR_0.5
A2: 40154 | B2: 0 | C2: 324 | D2: 1233 | E2: 19 | F2: 1213 | G2: 663 | H2: 175 | I2: 153 | J2: 0 | K2: 324 | O2: =(C2) -> 324 | P2: =(C2) -> 324 | Q2: =(C2) -> 324 | S2: 0.3
A3: 40161 | B3: 0 | C3: 236 | D3: 1304 | E3: 52 | F3: 1324 | G3: 572 | H3: 173 | I3: 644 | J3: 0 | K3: 236 | O3: =($S$1*C2+(1-$S$1)*O2) -> 324 | P3: =($S$2*C2+(1-$S$2)*P2) -> 324 | Q3: =($S$3*C2+(1-$S$3)*Q2) -> 324 | S3: 0.5 | V3: =ABS(C3-O3) -> 88 | W3: =ABS(C3-P3) -> 88 | X3: =ABS(C3-Q3) -> 88
A4: 40168 | B4: 0 | C4: 111 | D4: 36 | E4: 1 | F4: 82 | G4: 69 | H4: 19 | I4: 2 | J4: 0 | K4: 111 | O4: =($S$1*C3+(1-$S$1)*O3) -> 315.2 | P4: =($S$2*C3+(1-$S$2)*P3) -> 297.6 | Q4: =($S$3*C3+(1-$S$3)*Q3) -> 280 | V4: =ABS(C4-O4) -> 204.2 | W4: =ABS(C4-P4) -> 186.6 | X4: =ABS(C4-Q4) -> 169
A5: 40175 | B5: 0 | C5: 0 | D5: 0 | E5: 0 | F5: 0 | G5: 0 | H5: 0 | I5: 0 | J5: 0 | K5: 0 | L5: =AVERAGE(C2:C4) -> 223.66667 | M5: =(C5-L5) -> -223.66667 | N5: =ABS(M5) -> 223.66667 | O5: =($S$1*C4+(1-$S$1)*O4) -> 294.78 | P5: =($S$2*C4+(1-$S$2)*P4) -> 241.62 | Q5: =($S$3*C4+(1-$S$3)*Q4) -> 195.5 | V5: =ABS(C5-O5) -> 294.78 | W5: =ABS(C5-P5) -> 241.62 | X5: =ABS(C5-Q5) -> 195.5
A6: 40182 | B6: 0 | C6: 324 | D6: 1152 | E6: 47 | F6: 168 | G6: 0 | H6: 17 | I6: 21 | J6: 0 | K6: 324 | L6: =AVERAGE(C3:C5) -> 115.66667 | M6: =(C6-L6) -> 208.33333 | N6: =ABS(M6) -> 208.33333 | O6: =($S$1*C5+(1-$S$1)*O5) -> 265.302 | P6: =($S$2*C5+(1-$S$2)*P5) -> 169.134 | Q6: =($S$3*C5+(1-$S$3)*Q5) -> 97.75 | V6: =ABS(C6-O6) -> 58.698 | W6: =ABS(C6-P6) -> 154.866 | X6: =ABS(C6-Q6) -> 226.25
A7: 40189 | B7: 0 | C7: 190 | D7: 928 | E7: 64 | F7: 233 | G7: 20 | H7: 23 | I7: 72 | J7: 0 | K7: 190 | L7: =AVERAGE(C4:C6) -> 145 | M7: =(C7-L7) -> 45 | N7: =ABS(M7) -> 45 | O7: =($S$1*C6+(1-$S$1)*O6) -> 271.1718 | P7: =($S$2*C6+(1-$S$2)*P6) -> 215.5938 | Q7: =($S$3*C6+(1-$S$3)*Q6) -> 210.875 | V7: =ABS(C7-O7) -> 81.1718 | W7: =ABS(C7-P7) -> 25.5938 | X7: =ABS(C7-Q7) -> 20.875
A8: 40196 | B8: 0 | C8: 479 | D8: 627 | E8: 49 | F8: 897 | G8: 3 | H8: 0 | I8: 23 | J8: 0 | K8: 479 | L8: =AVERAGE(C5:C7) -> 171.33333 | M8: =(C8-L8) -> 307.66667 | N8: =ABS(M8) -> 307.66667 | O8: =($S$1*C7+(1-$S$1)*O7) -> 263.05462 | P8: =($S$2*C7+(1-$S$2)*P7) -> 207.91566 | Q8: =($S$3*C7+(1-$S$3)*Q7) -> 200.4375 | V8: =ABS(C8-O8) -> 215.94538 | W8: =ABS(C8-P8) -> 271.08434 | X8: =ABS(C8-Q8) -> 278.5625
A9: 40203 | B9: 0 | C9: 504 | D9: 864 | E9: 186 | F9: 211 | G9: 0 | H9: 0 | I9: 621 | J9: 114 | K9: 504 | L9: =AVERAGE(C6:C8) -> 331 | M9: =(C9-L9) -> 173 | N9: =ABS(M9) -> 173 | O9: =($S$1*C8+(1-$S$1)*O8) -> 284.64916 | P9: =($S$2*C8+(1-$S$2)*P8) -> 289.24096 | Q9: =($S$3*C8+(1-$S$3)*Q8) -> 339.71875 | V9: =ABS(C9-O9) -> 219.35084 | W9: =ABS(C9-P9) -> 214.75904 | X9: =ABS(C9-Q9) -> 164.28125
A10: 40210 | B10: 0 | C10: 326 | D10: 488 | E10: 53 | F10: 274 | G10: 0 | H10: 24 | I10: 81 | J10: 338 | K10: 326 | L10: =AVERAGE(C7:C9) -> 391 | M10: =(C10-L10) -> -65 | N10: =ABS(M10) -> 65 | O10: =($S$1*C9+(1-$S$1)*O9) -> 306.58424 | P10: =($S$2*C9+(1-$S$2)*P9) -> 353.66867 | Q10: =($S$3*C9+(1-$S$3)*Q9) -> 421.85938 | V10: =ABS(C10-O10) -> 19.415758 | W10: =ABS(C10-P10) -> 27.668673 | X10: =ABS(C10-Q10) -> 95.859375
A11: 40217 | B11: 0 | C11: 213 | D11: 547 | E11: 51 | F11: 512 | G11: 0 | H11: 0 | I11: 68 | J11: 314 | K11: 213 | L11: =AVERAGE(C8:C10) -> 436.33333 | M11: =(C11-L11) -> -223.33333 | N11: =ABS(M11) -> 223.33333 | O11: =($S$1*C10+(1-$S$1)*O10) -> 308.52582 | P11: =($S$2*C10+(1-$S$2)*P10) -> 345.36807 | Q11: =($S$3*C10+(1-$S$3)*Q10) -> 373.92969 | V11: =ABS(C11-O11) -> 95.525818 | W11: =ABS(C11-P11) -> 132.36807 | X11: =ABS(C11-Q11) -> 160.92969
A12: 40224 | B12: 0 | C12: 442 | D12: 1014 | E12: 159 | F12: 587 | G12: 0 | H12: 1 | I12: 19 | J12: 720 | K12: 442 | L12: =AVERAGE(C9:C11) -> 347.66667 | M12: =(C12-L12) -> 94.333333 | N12: =ABS(M12) -> 94.333333 | O12: =($S$1*C11+(1-$S$1)*O11) -> 298.97324 | P12: =($S$2*C11+(1-$S$2)*P11) -> 305.65765 | Q12: =($S$3*C11+(1-$S$3)*Q11) -> 293.46484 | V12: =ABS(C12-O12) -> 143.02676 | W12: =ABS(C12-P12) -> 136.34235 | X12: =ABS(C12-Q12) -> 148.53516
A13: 40231 | B13: 0 | C13: 272 | D13: 613 | E13: 79 | F13: 294 | G13: 0 | H13: 0 | I13: 1407 | J13: 551 | K13: 272 | L13: =AVERAGE(C10:C12) -> 327 | M13: =(C13-L13) -> -55 | N13: =ABS(M13) -> 55 | O13: =($S$1*C12+(1-$S$1)*O12) -> 313.27591 | P13: =($S$2*C12+(1-$S$2)*P12) -> 346.56036 | Q13: =($S$3*C12+(1-$S$3)*Q12) -> 367.73242 | V13: =ABS(C13-O13) -> 41.275913 | W13: =ABS(C13-P13) -> 74.560355 | X13: =ABS(C13-Q13) -> 95.732422
A14: 40238 | B14: 0 | C14: 409 | D14: 754 | E14: 78 | F14: 735 | G14: 3 | H14: 2 | I14: 133 | J14: 306 | K14: 409 | L14: =AVERAGE(C11:C13) -> 309 | M14: =(C14-L14) -> 100 | N14: =ABS(M14) -> 100 | O14: =($S$1*C13+(1-$S$1)*O13) -> 309.14832 | P14: =($S$2*C13+(1-$S$2)*P13) -> 324.19225 | Q14: =($S$3*C13+(1-$S$3)*Q13) -> 319.86621 | V14: =ABS(C14-O14) -> 99.851679 | W14: =ABS(C14-P14) -> 84.807752 | X14: =ABS(C14-Q14) -> 89.133789
A15: 40245 | B15: 0 | C15: 337 | D15: 800 | E15: 262 | F15: 917 | G15: 0 | H15: 0 | I15: 47 | J15: 405 | K15: 337 | L15: =AVERAGE(C12:C14) -> 374.33333 | M15: =(C15-L15) -> -37.333333 | N15: =ABS(M15) -> 37.333333 | O15: =($S$1*C14+(1-$S$1)*O14) -> 319.13349 | P15: =($S$2*C14+(1-$S$2)*P14) -> 349.63457 | Q15: =($S$3*C14+(1-$S$3)*Q14) -> 364.43311 | V15: =ABS(C15-O15) -> 17.866511 | W15: =ABS(C15-P15) -> 12.634574 | X15: =ABS(C15-Q15) -> 27.433105
A16: 40252 | B16: 194 | C16: 375 | D16: 555 | E16: 224 | F16: 551 | G16: 12 | H16: 0 | I16: 826 | J16: 179 | K16: 375 | L16: =AVERAGE(C13:C15) -> 339.33333 | M16: =(C16-L16) -> 35.666667 | N16: =ABS(M16) -> 35.666667 | O16: =($S$1*C15+(1-$S$1)*O15) -> 320.92014 | P16: =($S$2*C15+(1-$S$2)*P15) -> 345.8442 | Q16: =($S$3*C15+(1-$S$3)*Q15) -> 350.71655 | V16: =ABS(C16-O16) -> 54.07986 | W16: =ABS(C16-P16) -> 29.155798 | X16: =ABS(C16-Q16) -> 24.283447
... A105: 40875 | B105: 226 | C105: 331 | D105: 1040 | E105: 105 | F105: 953 | G105: 1564 | H105: 314 | I105: 3275 | J105: 436 | K105: 331 | L105: =AVERAGE(C102:C104) -> 494 | M105: =(C105-L105) -> -163 | N105: =ABS(M105) -> 163 | O105: =($S$1*C104+(1-$S$1)*O104) -> 394.38964 | P105: =($S$2*C104+(1-$S$2)*P104) -> 405.96357 | Q105: =($S$3*C104+(1-$S$3)*Q104) -> 404.21419 | V105: =ABS(C105-O105) -> 63.389641 | W105: =ABS(C105-P105) -> 74.963566 | X105: =ABS(C105-Q105) -> 73.214189
T106: MAD _M3 | U106: =AVERAGE(N94:N105) -> 130.08333
T107: MAD _ES_0.1 | U107: =AVERAGE(V94:V105) -> 114.92427
T108: MAD _ES_0.3 | U108: =AVERAGE(W94:W105) -> 120.42201
T109: MAD _ES_0.5 | U109: =AVERAGE(X94:X105) -> 125.1226
V111: AVERAGE | W111: STD DEV
V112: =AVERAGE(C2:C105) -> 378.50962 | W112: =STDEV(C2:C105) -> 175.84702

Sheet POPCORN HOLDER
A1: Week_start | B1: 22423 REGENCY CAKESTAND 3 TI | C1: 85123A WHITE HANGING HEART T- | D1: 85099B JUMBO BAG RED RETROSPO | E1: 47566 PARTY BUNTING | F1: 84879 ASSORTED COLOUR BIRD O | G1: 22086 PAPER CHAIN KIT 50'S C | H1: 79321 CHILLI LIGHTS | I1: 22197 SMALL POPCORN HOLDER | J1: 22386 JUMBO BAG PINK POLKADO | K1: 20725 LUNCH BAG RED RETROSPO | L1: MA3_FORECAST | M1: ERROR | N1: ABS ERROR | O1: ES_0.1 | P1: ES_0.3 | Q1: ES_0.5 | R1: ALPHA | S1: 0.1 | V1: ABSERR_0.1 | W1: ABSERR_0.3 | X1: ABSERR_0.5
A2: 40154 | B2: 0 | C2: 153 | D2: 1233 | E2: 19 | F2: 1213 | G2: 663 | H2: 175 | I2: 153 | J2: 0 | K2: 324 | O2: =(C2) -> 153 | P2: =(C2) -> 153 | Q2: =(C2) -> 153 | S2: 0.3
A3: 40161 | B3: 0 | C3: 644 | D3: 1304 | E3: 52 | F3: 1324 | G3: 572 | H3: 173 | I3: 644 | J3: 0 | K3: 236 | O3: =($S$1*C2+(1-$S$1)*O2) -> 153 | P3: =($S$2*C2+(1-$S$2)*P2) -> 153 | Q3: =($S$3*C2+(1-$S$3)*Q2) -> 153 | S3: 0.5 | V3: =ABS(C3-O3) -> 491 | W3: =ABS(C3-P3) -> 491 | X3: =ABS(C3-Q3) -> 491
A4: 40168 | B4: 0 | C4: 2 | D4: 36 | E4: 1 | F4: 82 | G4: 69 | H4: 19 | I4: 2 | J4: 0 | K4: 111 | O4: =($S$1*C3+(1-$S$1)*O3) -> 202.1 | P4: =($S$2*C3+(1-$S$2)*P3) -> 300.3 | Q4: =($S$3*C3+(1-$S$3)*Q3) -> 398.5 | V4: =ABS(C4-O4) -> 200.1 | W4: =ABS(C4-P4) -> 298.3 | X4: =ABS(C4-Q4) -> 396.5
A5: 40175 | B5: 0 | C5: 0 | D5: 0 | E5: 0 | F5: 0 | G5: 0 | H5: 0 | I5: 0 | J5: 0 | K5: 0 | L5: =AVERAGE(C2:C4) -> 266.33333 | M5: =(C5-L5) -> -266.33333 | N5: =ABS(M5) -> 266.33333 | O5: =($S$1*C4+(1-$S$1)*O4) -> 182.09 | P5: =($S$2*C4+(1-$S$2)*P4) -> 210.81 | Q5: =($S$3*C4+(1-$S$3)*Q4) -> 200.25 | V5: =ABS(C5-O5) -> 182.09 | W5: =ABS(C5-P5) -> 210.81 | X5: =ABS(C5-Q5) -> 200.25
A6: 40182 | B6: 0 | C6: 21 | D6: 1152 | E6: 47 | F6: 168 | G6: 0 | H6: 17 | I6: 21 | J6: 0 | K6: 324 | L6: =AVERAGE(C3:C5) -> 215.33333 | M6: =(C6-L6) -> -194.33333 | N6: =ABS(M6) -> 194.33333 | O6: =($S$1*C5+(1-$S$1)*O5) -> 163.881 | P6: =($S$2*C5+(1-$S$2)*P5) -> 147.567 | Q6: =($S$3*C5+(1-$S$3)*Q5) -> 100.125 | V6: =ABS(C6-O6) -> 142.881 | W6: =ABS(C6-P6) -> 126.567 | X6: =ABS(C6-Q6) -> 79.125
A7: 40189 | B7: 0 | C7: 72 | D7: 928 | E7: 64 | F7: 233 | G7: 20 | H7: 23 | I7: 72 | J7: 0 | K7: 190 | L7: =AVERAGE(C4:C6) -> 7.6666667 | M7: =(C7-L7) -> 64.333333 | N7: =ABS(M7) -> 64.333333 | O7: =($S$1*C6+(1-$S$1)*O6) -> 149.5929 | P7: =($S$2*C6+(1-$S$2)*P6) -> 109.5969 | Q7: =($S$3*C6+(1-$S$3)*Q6) -> 60.5625 | V7: =ABS(C7-O7) -> 77.5929 | W7: =ABS(C7-P7) -> 37.5969 | X7: =ABS(C7-Q7) -> 11.4375
A8: 40196 | B8: 0 | C8: 23 | D8: 627 | E8: 49 | F8: 897 | G8: 3 | H8: 0 | I8: 23 | J8: 0 | K8: 479 | L8: =AVERAGE(C5:C7) -> 31 | M8: =(C8-L8) -> -8 | N8: =ABS(M8) -> 8 | O8: =($S$1*C7+(1-$S$1)*O7) -> 141.83361 | P8: =($S$2*C7+(1-$S$2)*P7) -> 98.31783 | Q8: =($S$3*C7+(1-$S$3)*Q7) -> 66.28125 | V8: =ABS(C8-O8) -> 118.83361 | W8: =ABS(C8-P8) -> 75.31783 | X8: =ABS(C8-Q8) -> 43.28125
A9: 40203 | B9: 0 | C9: 621 | D9: 864 | E9: 186 | F9: 211 | G9: 0 | H9: 0 | I9: 621 | J9: 114 | K9: 504 | L9: =AVERAGE(C6:C8) -> 38.666667 | M9: =(C9-L9) -> 582.33333 | N9: =ABS(M9) -> 582.33333 | O9: =($S$1*C8+(1-$S$1)*O8) -> 129.95025 | P9: =($S$2*C8+(1-$S$2)*P8) -> 75.722481 | Q9: =($S$3*C8+(1-$S$3)*Q8) -> 44.640625 | V9: =ABS(C9-O9) -> 491.04975 | W9: =ABS(C9-P9) -> 545.27752 | X9: =ABS(C9-Q9) -> 576.35938
A10: 40210 | B10: 0 | C10: 81 | D10: 488 | E10: 53 | F10: 274 | G10: 0 | H10: 24 | I10: 81 | J10: 338 | K10: 326 | L10: =AVERAGE(C7:C9) -> 238.66667 | M10: =(C10-L10) -> -157.66667 | N10: =ABS(M10) -> 157.66667 | O10: =($S$1*C9+(1-$S$1)*O9) -> 179.05522 | P10: =($S$2*C9+(1-$S$2)*P9) -> 239.30574 | Q10: =($S$3*C9+(1-$S$3)*Q9) -> 332.82031 | V10: =ABS(C10-O10) -> 98.055224 | W10: =ABS(C10-P10) -> 158.30574 | X10: =ABS(C10-Q10) -> 251.82031
A11: 40217 | B11: 0 | C11: 68 | D11: 547 | E11: 51 | F11: 512 | G11: 0 | H11: 0 | I11: 68 | J11: 314 | K11: 213 | L11: =AVERAGE(C8:C10) -> 241.66667 | M11: =(C11-L11) -> -173.66667 | N11: =ABS(M11) -> 173.66667 | O11: =($S$1*C10+(1-$S$1)*O10) -> 169.2497 | P11: =($S$2*C10+(1-$S$2)*P10) -> 191.81402 | Q11: =($S$3*C10+(1-$S$3)*Q10) -> 206.91016 | V11: =ABS(C11-O11) -> 101.2497 | W11: =ABS(C11-P11) -> 123.81402 | X11: =ABS(C11-Q11) -> 138.91016
A12: 40224 | B12: 0 | C12: 19 | D12: 1014 | E12: 159 | F12: 587 | G12: 0 | H12: 1 | I12: 19 | J12: 720 | K12: 442 | L12: =AVERAGE(C9:C11) -> 256.66667 | M12: =(C12-L12) -> -237.66667 | N12: =ABS(M12) -> 237.66667 | O12: =($S$1*C11+(1-$S$1)*O11) -> 159.12473 | P12: =($S$2*C11+(1-$S$2)*P11) -> 154.66981 | Q12: =($S$3*C11+(1-$S$3)*Q11) -> 137.45508 | V12: =ABS(C12-O12) -> 140.12473 | W12: =ABS(C12-P12) -> 135.66981 | X12: =ABS(C12-Q12) -> 118.45508
A13: 40231 | B13: 0 | C13: 1407 | D13: 613 | E13: 79 | F13: 294 | G13: 0 | H13: 0 | I13: 1407 | J13: 551 | K13: 272 | L13: =AVERAGE(C10:C12) -> 56 | M13: =(C13-L13) -> 1351 | N13: =ABS(M13) -> 1351 | O13: =($S$1*C12+(1-$S$1)*O12) -> 145.11226 | P13: =($S$2*C12+(1-$S$2)*P12) -> 113.96887 | Q13: =($S$3*C12+(1-$S$3)*Q12) -> 78.227539 | V13: =ABS(C13-O13) -> 1261.8877 | W13: =ABS(C13-P13) -> 1293.0311 | X13: =ABS(C13-Q13) -> 1328.7725
A14: 40238 | B14: 0 | C14: 133 | D14: 754 | E14: 78 | F14: 735 | G14: 3 | H14: 2 | I14: 133 | J14: 306 | K14: 409 | L14: =AVERAGE(C11:C13) -> 498 | M14: =(C14-L14) -> -365 | N14: =ABS(M14) -> 365 | O14: =($S$1*C13+(1-$S$1)*O13) -> 271.30103 | P14: =($S$2*C13+(1-$S$2)*P13) -> 501.87821 | Q14: =($S$3*C13+(1-$S$3)*Q13) -> 742.61377 | V14: =ABS(C14-O14) -> 138.30103 | W14: =ABS(C14-P14) -> 368.87821 | X14: =ABS(C14-Q14) -> 609.61377
A15: 40245 | B15: 0 | C15: 47 | D15: 800 | E15: 262 | F15: 917 | G15: 0 | H15: 0 | I15: 47 | J15: 405 | K15: 337 | L15: =AVERAGE(C12:C14) -> 519.66667 | M15: =(C15-L15) -> -472.66667 | N15: =ABS(M15) -> 472.66667 | O15: =($S$1*C14+(1-$S$1)*O14) -> 257.47093 | P15: =($S$2*C14+(1-$S$2)*P14) -> 391.21475 | Q15: =($S$3*C14+(1-$S$3)*Q14) -> 437.80688 | V15: =ABS(C15-O15) -> 210.47093 | W15: =ABS(C15-P15) -> 344.21475 | X15: =ABS(C15-Q15) -> 390.80688
A16: 40252 | B16: 194 | C16: 826 | D16: 555 | E16: 224 | F16: 551 | G16: 12 | H16: 0 | I16: 826 | J16: 179 | K16: 375 | L16: =AVERAGE(C13:C15) -> 529 | M16: =(C16-L16) -> 297 | N16: =ABS(M16) -> 297 | O16: =($S$1*C15+(1-$S$1)*O15) -> 236.42384 | P16: =($S$2*C15+(1-$S$2)*P15) -> 287.95032 | Q16: =($S$3*C15+(1-$S$3)*Q15) -> 242.40344 | V16: =ABS(C16-O16) -> 589.57616 | W16: =ABS(C16-P16) -> 538.04968 | X16: =ABS(C16-Q16) -> 583.59656
... A105: 40875 | B105: 226 | C105: 3275 | D105: 1040 | E105: 105 | F105: 953 | G105: 1564 | H105: 314 | I105: 3275 | J105: 436 | K105: 331 | L105: =AVERAGE(C102:C104) -> 3266.6667 | M105: =(C105-L105) -> 8.3333333 | N105: =ABS(M105) -> 8.3333333 | O105: =($S$1*C104+(1-$S$1)*O104) -> 1679.671 | P105: =($S$2*C104+(1-$S$2)*P104) -> 2547.9695 | Q105: =($S$3*C104+(1-$S$3)*Q104) -> 2843.1456 | V105: =ABS(C105-O105) -> 1595.329 | W105: =ABS(C105-P105) -> 727.03051 | X105: =ABS(C105-Q105) -> 431.85444
T106: MAD _M3 | U106: =AVERAGE(N94:N105) -> 555.66667
T107: MAD _ES_0.1 | U107: =AVERAGE(V94:V105) -> 906.81305
T108: MAD _ES_0.3 | U108: =AVERAGE(W94:W105) -> 698.18562
T109: MAD _ES_0.5 | U109: =AVERAGE(X94:X105) -> 646.26462
V111: AVERAGE | W111: STD DEV
V112: =AVERAGE(C2:C105) -> 799.71154 | W112: =STDEV(C2:C105) -> 903.03227

Sheet  REGENCY CAKESTAND 
A1: Week_start | B1: 22423 REGENCY CAKESTAND 3 TI | C1: 85123A WHITE HANGING HEART T- | D1: 85099B JUMBO BAG RED RETROSPO | E1: 47566 PARTY BUNTING | F1: 84879 ASSORTED COLOUR BIRD O | G1: 22086 PAPER CHAIN KIT 50'S C | H1: 79321 CHILLI LIGHTS | I1: 22197 SMALL POPCORN HOLDER | J1: 22386 JUMBO BAG PINK POLKADO | K1: 20725 LUNCH BAG RED RETROSPO | L1: MA3_FORECAST | M1: ERROR | N1: ABS ERROR | O1: ES_0.1 | P1: ES_0.3 | Q1: ES_0.5 | R1: ALPHA | S1: 0.1 | V1: ABSERR_0.1 | W1: ABSERR_0.3 | X1: ABSERR_0.5
A2: 40154 | B2: 0 | C2: 0 | D2: 1233 | E2: 19 | F2: 1213 | G2: 663 | H2: 175 | I2: 153 | J2: 0 | K2: 324 | O2: =(C2) -> 0 | P2: =(C2) -> 0 | Q2: =(C2) -> 0 | S2: 0.3
A3: 40161 | B3: 0 | C3: 0 | D3: 1304 | E3: 52 | F3: 1324 | G3: 572 | H3: 173 | I3: 644 | J3: 0 | K3: 236 | O3: =($S$1*C2+(1-$S$1)*O2) -> 0 | P3: =($S$2*C2+(1-$S$2)*P2) -> 0 | Q3: =($S$3*C2+(1-$S$3)*Q2) -> 0 | S3: 0.5 | V3: =ABS(C3-O3) -> 0 | W3: =ABS(C3-P3) -> 0 | X3: =ABS(C3-Q3) -> 0
A4: 40168 | B4: 0 | C4: 0 | D4: 36 | E4: 1 | F4: 82 | G4: 69 | H4: 19 | I4: 2 | J4: 0 | K4: 111 | O4: =($S$1*C3+(1-$S$1)*O3) -> 0 | P4: =($S$2*C3+(1-$S$2)*P3) -> 0 | Q4: =($S$3*C3+(1-$S$3)*Q3) -> 0 | V4: =ABS(C4-O4) -> 0 | W4: =ABS(C4-P4) -> 0 | X4: =ABS(C4-Q4) -> 0
A5: 40175 | B5: 0 | C5: 0 | D5: 0 | E5: 0 | F5: 0 | G5: 0 | H5: 0 | I5: 0 | J5: 0 | K5: 0 | L5: =AVERAGE(C2:C4) -> 0 | M5: =(C5-L5) -> 0 | N5: =ABS(M5) -> 0 | O5: =($S$1*C4+(1-$S$1)*O4) -> 0 | P5: =($S$2*C4+(1-$S$2)*P4) -> 0 | Q5: =($S$3*C4+(1-$S$3)*Q4) -> 0 | V5: =ABS(C5-O5) -> 0 | W5: =ABS(C5-P5) -> 0 | X5: =ABS(C5-Q5) -> 0
A6: 40182 | B6: 0 | C6: 0 | D6: 1152 | E6: 47 | F6: 168 | G6: 0 | H6: 17 | I6: 21 | J6: 0 | K6: 324 | L6: =AVERAGE(C3:C5) -> 0 | M6: =(C6-L6) -> 0 | N6: =ABS(M6) -> 0 | O6: =($S$1*C5+(1-$S$1)*O5) -> 0 | P6: =($S$2*C5+(1-$S$2)*P5) -> 0 | Q6: =($S$3*C5+(1-$S$3)*Q5) -> 0 | V6: =ABS(C6-O6) -> 0 | W6: =ABS(C6-P6) -> 0 | X6: =ABS(C6-Q6) -> 0
A7: 40189 | B7: 0 | C7: 0 | D7: 928 | E7: 64 | F7: 233 | G7: 20 | H7: 23 | I7: 72 | J7: 0 | K7: 190 | L7: =AVERAGE(C4:C6) -> 0 | M7: =(C7-L7) -> 0 | N7: =ABS(M7) -> 0 | O7: =($S$1*C6+(1-$S$1)*O6) -> 0 | P7: =($S$2*C6+(1-$S$2)*P6) -> 0 | Q7: =($S$3*C6+(1-$S$3)*Q6) -> 0 | V7: =ABS(C7-O7) -> 0 | W7: =ABS(C7-P7) -> 0 | X7: =ABS(C7-Q7) -> 0
A8: 40196 | B8: 0 | C8: 0 | D8: 627 | E8: 49 | F8: 897 | G8: 3 | H8: 0 | I8: 23 | J8: 0 | K8: 479 | L8: =AVERAGE(C5:C7) -> 0 | M8: =(C8-L8) -> 0 | N8: =ABS(M8) -> 0 | O8: =($S$1*C7+(1-$S$1)*O7) -> 0 | P8: =($S$2*C7+(1-$S$2)*P7) -> 0 | Q8: =($S$3*C7+(1-$S$3)*Q7) -> 0 | V8: =ABS(C8-O8) -> 0 | W8: =ABS(C8-P8) -> 0 | X8: =ABS(C8-Q8) -> 0
A9: 40203 | B9: 0 | C9: 0 | D9: 864 | E9: 186 | F9: 211 | G9: 0 | H9: 0 | I9: 621 | J9: 114 | K9: 504 | L9: =AVERAGE(C6:C8) -> 0 | M9: =(C9-L9) -> 0 | N9: =ABS(M9) -> 0 | O9: =($S$1*C8+(1-$S$1)*O8) -> 0 | P9: =($S$2*C8+(1-$S$2)*P8) -> 0 | Q9: =($S$3*C8+(1-$S$3)*Q8) -> 0 | V9: =ABS(C9-O9) -> 0 | W9: =ABS(C9-P9) -> 0 | X9: =ABS(C9-Q9) -> 0
A10: 40210 | B10: 0 | C10: 0 | D10: 488 | E10: 53 | F10: 274 | G10: 0 | H10: 24 | I10: 81 | J10: 338 | K10: 326 | L10: =AVERAGE(C7:C9) -> 0 | M10: =(C10-L10) -> 0 | N10: =ABS(M10) -> 0 | O10: =($S$1*C9+(1-$S$1)*O9) -> 0 | P10: =($S$2*C9+(1-$S$2)*P9) -> 0 | Q10: =($S$3*C9+(1-$S$3)*Q9) -> 0 | V10: =ABS(C10-O10) -> 0 | W10: =ABS(C10-P10) -> 0 | X10: =ABS(C10-Q10) -> 0
A11: 40217 | B11: 0 | C11: 0 | D11: 547 | E11: 51 | F11: 512 | G11: 0 | H11: 0 | I11: 68 | J11: 314 | K11: 213 | L11: =AVERAGE(C8:C10) -> 0 | M11: =(C11-L11) -> 0 | N11: =ABS(M11) -> 0 | O11: =($S$1*C10+(1-$S$1)*O10) -> 0 | P11: =($S$2*C10+(1-$S$2)*P10) -> 0 | Q11: =($S$3*C10+(1-$S$3)*Q10) -> 0 | V11: =ABS(C11-O11) -> 0 | W11: =ABS(C11-P11) -> 0 | X11: =ABS(C11-Q11) -> 0
A12: 40224 | B12: 0 | C12: 0 | D12: 1014 | E12: 159 | F12: 587 | G12: 0 | H12: 1 | I12: 19 | J12: 720 | K12: 442 | L12: =AVERAGE(C9:C11) -> 0 | M12: =(C12-L12) -> 0 | N12: =ABS(M12) -> 0 | O12: =($S$1*C11+(1-$S$1)*O11) -> 0 | P12: =($S$2*C11+(1-$S$2)*P11) -> 0 | Q12: =($S$3*C11+(1-$S$3)*Q11) -> 0 | V12: =ABS(C12-O12) -> 0 | W12: =ABS(C12-P12) -> 0 | X12: =ABS(C12-Q12) -> 0
A13: 40231 | B13: 0 | C13: 0 | D13: 613 | E13: 79 | F13: 294 | G13: 0 | H13: 0 | I13: 1407 | J13: 551 | K13: 272 | L13: =AVERAGE(C10:C12) -> 0 | M13: =(C13-L13) -> 0 | N13: =ABS(M13) -> 0 | O13: =($S$1*C12+(1-$S$1)*O12) -> 0 | P13: =($S$2*C12+(1-$S$2)*P12) -> 0 | Q13: =($S$3*C12+(1-$S$3)*Q12) -> 0 | V13: =ABS(C13-O13) -> 0 | W13: =ABS(C13-P13) -> 0 | X13: =ABS(C13-Q13) -> 0
A14: 40238 | B14: 0 | C14: 0 | D14: 754 | E14: 78 | F14: 735 | G14: 3 | H14: 2 | I14: 133 | J14: 306 | K14: 409 | L14: =AVERAGE(C11:C13) -> 0 | M14: =(C14-L14) -> 0 | N14: =ABS(M14) -> 0 | O14: =($S$1*C13+(1-$S$1)*O13) -> 0 | P14: =($S$2*C13+(1-$S$2)*P13) -> 0 | Q14: =($S$3*C13+(1-$S$3)*Q13) -> 0 | V14: =ABS(C14-O14) -> 0 | W14: =ABS(C14-P14) -> 0 | X14: =ABS(C14-Q14) -> 0
A15: 40245 | B15: 0 | C15: 0 | D15: 800 | E15: 262 | F15: 917 | G15: 0 | H15: 0 | I15: 47 | J15: 405 | K15: 337 | L15: =AVERAGE(C12:C14) -> 0 | M15: =(C15-L15) -> 0 | N15: =ABS(M15) -> 0 | O15: =($S$1*C14+(1-$S$1)*O14) -> 0 | P15: =($S$2*C14+(1-$S$2)*P14) -> 0 | Q15: =($S$3*C14+(1-$S$3)*Q14) -> 0 | V15: =ABS(C15-O15) -> 0 | W15: =ABS(C15-P15) -> 0 | X15: =ABS(C15-Q15) -> 0
A16: 40252 | B16: 194 | C16: 194 | D16: 555 | E16: 224 | F16: 551 | G16: 12 | H16: 0 | I16: 826 | J16: 179 | K16: 375 | L16: =AVERAGE(C13:C15) -> 0 | M16: =(C16-L16) -> 194 | N16: =ABS(M16) -> 194 | O16: =($S$1*C15+(1-$S$1)*O15) -> 0 | P16: =($S$2*C15+(1-$S$2)*P15) -> 0 | Q16: =($S$3*C15+(1-$S$3)*Q15) -> 0 | V16: =ABS(C16-O16) -> 194 | W16: =ABS(C16-P16) -> 194 | X16: =ABS(C16-Q16) -> 194
... A105: 40875 | B105: 226 | C105: 226 | D105: 1040 | E105: 105 | F105: 953 | G105: 1564 | H105: 314 | I105: 3275 | J105: 436 | K105: 331 | L105: =AVERAGE(C102:C104) -> 217 | M105: =(C105-L105) -> 9 | N105: =ABS(M105) -> 9 | O105: =($S$1*C104+(1-$S$1)*O104) -> 220.78658 | P105: =($S$2*C104+(1-$S$2)*P104) -> 226.86719 | Q105: =($S$3*C104+(1-$S$3)*Q104) -> 233.60103 | V105: =ABS(C105-O105) -> 5.2134245 | W105: =ABS(C105-P105) -> 0.8671919 | X105: =ABS(C105-Q105) -> 7.6010286
T106: MAD _M3 | U106: =AVERAGE(N94:N105) -> 64.027778
T107: MAD _ES_0.1 | U107: =AVERAGE(V94:V105) -> 57.697315
T108: MAD _ES_0.3 | U108: =AVERAGE(W94:W105) -> 62.545069
T109: MAD _ES_0.5 | U109: =AVERAGE(X94:X105) -> 70.77462
V111: AVERAGE | W111: STD DEV
V112: =AVERAGE(C2:C105) -> 244.35577 | W112: =STDEV(C2:C105) -> 178.33686

Sheet CHILLI LIGHTS
A1: Week_start | B1: 22423 REGENCY CAKESTAND 3 TI | C1: 85123A WHITE HANGING HEART T- | D1: 85099B JUMBO BAG RED RETROSPO | E1: 47566 PARTY BUNTING | F1: 84879 ASSORTED COLOUR BIRD O | G1: 22086 PAPER CHAIN KIT 50'S C | H1: 79321 CHILLI LIGHTS | I1: 22197 SMALL POPCORN HOLDER | J1: 22386 JUMBO BAG PINK POLKADO | K1: 20725 LUNCH BAG RED RETROSPO | L1: MA3_FORECAST | M1: ERROR | N1: ABS ERROR | O1: ES_0.1 | P1: ES_0.3 | Q1: ES_0.5 | R1: ALPHA | S1: 0.1 | V1: ABSERR_0.1 | W1: ABSERR_0.3 | X1: ABSERR_0.5
A2: 40154 | B2: 0 | C2: 175 | D2: 1233 | E2: 19 | F2: 1213 | G2: 663 | H2: 175 | I2: 153 | J2: 0 | K2: 324 | O2: =(C2) -> 175 | P2: =(C2) -> 175 | Q2: =(C2) -> 175 | S2: 0.3
A3: 40161 | B3: 0 | C3: 173 | D3: 1304 | E3: 52 | F3: 1324 | G3: 572 | H3: 173 | I3: 644 | J3: 0 | K3: 236 | O3: =($S$1*C2+(1-$S$1)*O2) -> 175 | P3: =($S$2*C2+(1-$S$2)*P2) -> 175 | Q3: =($S$3*C2+(1-$S$3)*Q2) -> 175 | S3: 0.5 | V3: =ABS(C3-O3) -> 2 | W3: =ABS(C3-P3) -> 2 | X3: =ABS(C3-Q3) -> 2
A4: 40168 | B4: 0 | C4: 19 | D4: 36 | E4: 1 | F4: 82 | G4: 69 | H4: 19 | I4: 2 | J4: 0 | K4: 111 | O4: =($S$1*C3+(1-$S$1)*O3) -> 174.8 | P4: =($S$2*C3+(1-$S$2)*P3) -> 174.4 | Q4: =($S$3*C3+(1-$S$3)*Q3) -> 174 | V4: =ABS(C4-O4) -> 155.8 | W4: =ABS(C4-P4) -> 155.4 | X4: =ABS(C4-Q4) -> 155
A5: 40175 | B5: 0 | C5: 0 | D5: 0 | E5: 0 | F5: 0 | G5: 0 | H5: 0 | I5: 0 | J5: 0 | K5: 0 | L5: =AVERAGE(C2:C4) -> 122.33333 | M5: =(C5-L5) -> -122.33333 | N5: =ABS(M5) -> 122.33333 | O5: =($S$1*C4+(1-$S$1)*O4) -> 159.22 | P5: =($S$2*C4+(1-$S$2)*P4) -> 127.78 | Q5: =($S$3*C4+(1-$S$3)*Q4) -> 96.5 | V5: =ABS(C5-O5) -> 159.22 | W5: =ABS(C5-P5) -> 127.78 | X5: =ABS(C5-Q5) -> 96.5
A6: 40182 | B6: 0 | C6: 17 | D6: 1152 | E6: 47 | F6: 168 | G6: 0 | H6: 17 | I6: 21 | J6: 0 | K6: 324 | L6: =AVERAGE(C3:C5) -> 64 | M6: =(C6-L6) -> -47 | N6: =ABS(M6) -> 47 | O6: =($S$1*C5+(1-$S$1)*O5) -> 143.298 | P6: =($S$2*C5+(1-$S$2)*P5) -> 89.446 | Q6: =($S$3*C5+(1-$S$3)*Q5) -> 48.25 | V6: =ABS(C6-O6) -> 126.298 | W6: =ABS(C6-P6) -> 72.446 | X6: =ABS(C6-Q6) -> 31.25
A7: 40189 | B7: 0 | C7: 23 | D7: 928 | E7: 64 | F7: 233 | G7: 20 | H7: 23 | I7: 72 | J7: 0 | K7: 190 | L7: =AVERAGE(C4:C6) -> 12 | M7: =(C7-L7) -> 11 | N7: =ABS(M7) -> 11 | O7: =($S$1*C6+(1-$S$1)*O6) -> 130.6682 | P7: =($S$2*C6+(1-$S$2)*P6) -> 67.7122 | Q7: =($S$3*C6+(1-$S$3)*Q6) -> 32.625 | V7: =ABS(C7-O7) -> 107.6682 | W7: =ABS(C7-P7) -> 44.7122 | X7: =ABS(C7-Q7) -> 9.625
A8: 40196 | B8: 0 | C8: 0 | D8: 627 | E8: 49 | F8: 897 | G8: 3 | H8: 0 | I8: 23 | J8: 0 | K8: 479 | L8: =AVERAGE(C5:C7) -> 13.333333 | M8: =(C8-L8) -> -13.333333 | N8: =ABS(M8) -> 13.333333 | O8: =($S$1*C7+(1-$S$1)*O7) -> 119.90138 | P8: =($S$2*C7+(1-$S$2)*P7) -> 54.29854 | Q8: =($S$3*C7+(1-$S$3)*Q7) -> 27.8125 | V8: =ABS(C8-O8) -> 119.90138 | W8: =ABS(C8-P8) -> 54.29854 | X8: =ABS(C8-Q8) -> 27.8125
A9: 40203 | B9: 0 | C9: 0 | D9: 864 | E9: 186 | F9: 211 | G9: 0 | H9: 0 | I9: 621 | J9: 114 | K9: 504 | L9: =AVERAGE(C6:C8) -> 13.333333 | M9: =(C9-L9) -> -13.333333 | N9: =ABS(M9) -> 13.333333 | O9: =($S$1*C8+(1-$S$1)*O8) -> 107.91124 | P9: =($S$2*C8+(1-$S$2)*P8) -> 38.008978 | Q9: =($S$3*C8+(1-$S$3)*Q8) -> 13.90625 | V9: =ABS(C9-O9) -> 107.91124 | W9: =ABS(C9-P9) -> 38.008978 | X9: =ABS(C9-Q9) -> 13.90625
A10: 40210 | B10: 0 | C10: 24 | D10: 488 | E10: 53 | F10: 274 | G10: 0 | H10: 24 | I10: 81 | J10: 338 | K10: 326 | L10: =AVERAGE(C7:C9) -> 7.6666667 | M10: =(C10-L10) -> 16.333333 | N10: =ABS(M10) -> 16.333333 | O10: =($S$1*C9+(1-$S$1)*O9) -> 97.120118 | P10: =($S$2*C9+(1-$S$2)*P9) -> 26.606285 | Q10: =($S$3*C9+(1-$S$3)*Q9) -> 6.953125 | V10: =ABS(C10-O10) -> 73.120118 | W10: =ABS(C10-P10) -> 2.6062846 | X10: =ABS(C10-Q10) -> 17.046875
A11: 40217 | B11: 0 | C11: 0 | D11: 547 | E11: 51 | F11: 512 | G11: 0 | H11: 0 | I11: 68 | J11: 314 | K11: 213 | L11: =AVERAGE(C8:C10) -> 8 | M11: =(C11-L11) -> -8 | N11: =ABS(M11) -> 8 | O11: =($S$1*C10+(1-$S$1)*O10) -> 89.808106 | P11: =($S$2*C10+(1-$S$2)*P10) -> 25.824399 | Q11: =($S$3*C10+(1-$S$3)*Q10) -> 15.476562 | V11: =ABS(C11-O11) -> 89.808106 | W11: =ABS(C11-P11) -> 25.824399 | X11: =ABS(C11-Q11) -> 15.476562
A12: 40224 | B12: 0 | C12: 1 | D12: 1014 | E12: 159 | F12: 587 | G12: 0 | H12: 1 | I12: 19 | J12: 720 | K12: 442 | L12: =AVERAGE(C9:C11) -> 8 | M12: =(C12-L12) -> -7 | N12: =ABS(M12) -> 7 | O12: =($S$1*C11+(1-$S$1)*O11) -> 80.827295 | P12: =($S$2*C11+(1-$S$2)*P11) -> 18.077079 | Q12: =($S$3*C11+(1-$S$3)*Q11) -> 7.7382812 | V12: =ABS(C12-O12) -> 79.827295 | W12: =ABS(C12-P12) -> 17.077079 | X12: =ABS(C12-Q12) -> 6.7382812
A13: 40231 | B13: 0 | C13: 0 | D13: 613 | E13: 79 | F13: 294 | G13: 0 | H13: 0 | I13: 1407 | J13: 551 | K13: 272 | L13: =AVERAGE(C10:C12) -> 8.3333333 | M13: =(C13-L13) -> -8.3333333 | N13: =ABS(M13) -> 8.3333333 | O13: =($S$1*C12+(1-$S$1)*O12) -> 72.844566 | P13: =($S$2*C12+(1-$S$2)*P12) -> 12.953956 | Q13: =($S$3*C12+(1-$S$3)*Q12) -> 4.3691406 | V13: =ABS(C13-O13) -> 72.844566 | W13: =ABS(C13-P13) -> 12.953956 | X13: =ABS(C13-Q13) -> 4.3691406
A14: 40238 | B14: 0 | C14: 2 | D14: 754 | E14: 78 | F14: 735 | G14: 3 | H14: 2 | I14: 133 | J14: 306 | K14: 409 | L14: =AVERAGE(C11:C13) -> 0.33333333 | M14: =(C14-L14) -> 1.6666667 | N14: =ABS(M14) -> 1.6666667 | O14: =($S$1*C13+(1-$S$1)*O13) -> 65.560109 | P14: =($S$2*C13+(1-$S$2)*P13) -> 9.0677689 | Q14: =($S$3*C13+(1-$S$3)*Q13) -> 2.1845703 | V14: =ABS(C14-O14) -> 63.560109 | W14: =ABS(C14-P14) -> 7.0677689 | X14: =ABS(C14-Q14) -> 0.18457031
A15: 40245 | B15: 0 | C15: 0 | D15: 800 | E15: 262 | F15: 917 | G15: 0 | H15: 0 | I15: 47 | J15: 405 | K15: 337 | L15: =AVERAGE(C12:C14) -> 1 | M15: =(C15-L15) -> -1 | N15: =ABS(M15) -> 1 | O15: =($S$1*C14+(1-$S$1)*O14) -> 59.204098 | P15: =($S$2*C14+(1-$S$2)*P14) -> 6.9474383 | Q15: =($S$3*C14+(1-$S$3)*Q14) -> 2.0922852 | V15: =ABS(C15-O15) -> 59.204098 | W15: =ABS(C15-P15) -> 6.9474383 | X15: =ABS(C15-Q15) -> 2.0922852
A16: 40252 | B16: 194 | C16: 0 | D16: 555 | E16: 224 | F16: 551 | G16: 12 | H16: 0 | I16: 826 | J16: 179 | K16: 375 | L16: =AVERAGE(C13:C15) -> 0.66666667 | M16: =(C16-L16) -> -0.66666667 | N16: =ABS(M16) -> 0.66666667 | O16: =($S$1*C15+(1-$S$1)*O15) -> 53.283689 | P16: =($S$2*C15+(1-$S$2)*P15) -> 4.8632068 | Q16: =($S$3*C15+(1-$S$3)*Q15) -> 1.0461426 | V16: =ABS(C16-O16) -> 53.283689 | W16: =ABS(C16-P16) -> 4.8632068 | X16: =ABS(C16-Q16) -> 1.0461426
... A105: 40875 | B105: 226 | C105: 314 | D105: 1040 | E105: 105 | F105: 953 | G105: 1564 | H105: 314 | I105: 3275 | J105: 436 | K105: 331 | L105: =AVERAGE(C102:C104) -> 610 | M105: =(C105-L105) -> -296 | N105: =ABS(M105) -> 296 | O105: =($S$1*C104+(1-$S$1)*O104) -> 285.75988 | P105: =($S$2*C104+(1-$S$2)*P104) -> 508.37837 | Q105: =($S$3*C104+(1-$S$3)*Q104) -> 664.44653 | V105: =ABS(C105-O105) -> 28.24012 | W105: =ABS(C105-P105) -> 194.37837 | X105: =ABS(C105-Q105) -> 350.44653
T106: MAD _M3 | U106: =AVERAGE(N94:N105) -> 173.75
T107: MAD _ES_0.1 | U107: =AVERAGE(V94:V105) -> 167.71517
T108: MAD _ES_0.3 | U108: =AVERAGE(W94:W105) -> 169.35865
T109: MAD _ES_0.5 | U109: =AVERAGE(X94:X105) -> 181.40984
V111: AVERAGE | W111: STD DEV
V112: =AVERAGE(C2:C105) -> 148.25 | W112: =STDEV(C2:C105) -> 190.58514

Sheet PAPER CHAIN KIT
A1: Week_start | B1: 22423 REGENCY CAKESTAND 3 TI | C1: 85123A WHITE HANGING HEART T- | D1: 85099B JUMBO BAG RED RETROSPO | E1: 47566 PARTY BUNTING | F1: 84879 ASSORTED COLOUR BIRD O | G1: 22086 PAPER CHAIN KIT 50'S C | H1: 79321 CHILLI LIGHTS | I1: 22197 SMALL POPCORN HOLDER | J1: 22386 JUMBO BAG PINK POLKADO | K1: 20725 LUNCH BAG RED RETROSPO | L1: MA3_FORECAST | M1: ERROR | N1: ABS ERROR | O1: ES_0.1 | P1: ES_0.3 | Q1: ES_0.5 | R1: ALPHA | S1: 0.1 | V1: ABSERR_0.1 | W1: ABSERR_0.3 | X1: ABSERR_0.5
A2: 40154 | B2: 0 | C2: 663 | D2: 1233 | E2: 19 | F2: 1213 | G2: 663 | H2: 175 | I2: 153 | J2: 0 | K2: 324 | O2: =(C2) -> 663 | P2: =(C2) -> 663 | Q2: =(C2) -> 663 | S2: 0.3
A3: 40161 | B3: 0 | C3: 572 | D3: 1304 | E3: 52 | F3: 1324 | G3: 572 | H3: 173 | I3: 644 | J3: 0 | K3: 236 | O3: =($S$1*C2+(1-$S$1)*O2) -> 663 | P3: =($S$2*C2+(1-$S$2)*P2) -> 663 | Q3: =($S$3*C2+(1-$S$3)*Q2) -> 663 | S3: 0.5 | V3: =ABS(C3-O3) -> 91 | W3: =ABS(C3-P3) -> 91 | X3: =ABS(C3-Q3) -> 91
A4: 40168 | B4: 0 | C4: 69 | D4: 36 | E4: 1 | F4: 82 | G4: 69 | H4: 19 | I4: 2 | J4: 0 | K4: 111 | O4: =($S$1*C3+(1-$S$1)*O3) -> 653.9 | P4: =($S$2*C3+(1-$S$2)*P3) -> 635.7 | Q4: =($S$3*C3+(1-$S$3)*Q3) -> 617.5 | V4: =ABS(C4-O4) -> 584.9 | W4: =ABS(C4-P4) -> 566.7 | X4: =ABS(C4-Q4) -> 548.5
A5: 40175 | B5: 0 | C5: 0 | D5: 0 | E5: 0 | F5: 0 | G5: 0 | H5: 0 | I5: 0 | J5: 0 | K5: 0 | L5: =AVERAGE(C2:C4) -> 434.66667 | M5: =(C5-L5) -> -434.66667 | N5: =ABS(M5) -> 434.66667 | O5: =($S$1*C4+(1-$S$1)*O4) -> 595.41 | P5: =($S$2*C4+(1-$S$2)*P4) -> 465.69 | Q5: =($S$3*C4+(1-$S$3)*Q4) -> 343.25 | V5: =ABS(C5-O5) -> 595.41 | W5: =ABS(C5-P5) -> 465.69 | X5: =ABS(C5-Q5) -> 343.25
A6: 40182 | B6: 0 | C6: 0 | D6: 1152 | E6: 47 | F6: 168 | G6: 0 | H6: 17 | I6: 21 | J6: 0 | K6: 324 | L6: =AVERAGE(C3:C5) -> 213.66667 | M6: =(C6-L6) -> -213.66667 | N6: =ABS(M6) -> 213.66667 | O6: =($S$1*C5+(1-$S$1)*O5) -> 535.869 | P6: =($S$2*C5+(1-$S$2)*P5) -> 325.983 | Q6: =($S$3*C5+(1-$S$3)*Q5) -> 171.625 | V6: =ABS(C6-O6) -> 535.869 | W6: =ABS(C6-P6) -> 325.983 | X6: =ABS(C6-Q6) -> 171.625
A7: 40189 | B7: 0 | C7: 20 | D7: 928 | E7: 64 | F7: 233 | G7: 20 | H7: 23 | I7: 72 | J7: 0 | K7: 190 | L7: =AVERAGE(C4:C6) -> 23 | M7: =(C7-L7) -> -3 | N7: =ABS(M7) -> 3 | O7: =($S$1*C6+(1-$S$1)*O6) -> 482.2821 | P7: =($S$2*C6+(1-$S$2)*P6) -> 228.1881 | Q7: =($S$3*C6+(1-$S$3)*Q6) -> 85.8125 | V7: =ABS(C7-O7) -> 462.2821 | W7: =ABS(C7-P7) -> 208.1881 | X7: =ABS(C7-Q7) -> 65.8125
A8: 40196 | B8: 0 | C8: 3 | D8: 627 | E8: 49 | F8: 897 | G8: 3 | H8: 0 | I8: 23 | J8: 0 | K8: 479 | L8: =AVERAGE(C5:C7) -> 6.6666667 | M8: =(C8-L8) -> -3.6666667 | N8: =ABS(M8) -> 3.6666667 | O8: =($S$1*C7+(1-$S$1)*O7) -> 436.05389 | P8: =($S$2*C7+(1-$S$2)*P7) -> 165.73167 | Q8: =($S$3*C7+(1-$S$3)*Q7) -> 52.90625 | V8: =ABS(C8-O8) -> 433.05389 | W8: =ABS(C8-P8) -> 162.73167 | X8: =ABS(C8-Q8) -> 49.90625
A9: 40203 | B9: 0 | C9: 0 | D9: 864 | E9: 186 | F9: 211 | G9: 0 | H9: 0 | I9: 621 | J9: 114 | K9: 504 | L9: =AVERAGE(C6:C8) -> 7.6666667 | M9: =(C9-L9) -> -7.6666667 | N9: =ABS(M9) -> 7.6666667 | O9: =($S$1*C8+(1-$S$1)*O8) -> 392.7485 | P9: =($S$2*C8+(1-$S$2)*P8) -> 116.91217 | Q9: =($S$3*C8+(1-$S$3)*Q8) -> 27.953125 | V9: =ABS(C9-O9) -> 392.7485 | W9: =ABS(C9-P9) -> 116.91217 | X9: =ABS(C9-Q9) -> 27.953125
A10: 40210 | B10: 0 | C10: 0 | D10: 488 | E10: 53 | F10: 274 | G10: 0 | H10: 24 | I10: 81 | J10: 338 | K10: 326 | L10: =AVERAGE(C7:C9) -> 7.6666667 | M10: =(C10-L10) -> -7.6666667 | N10: =ABS(M10) -> 7.6666667 | O10: =($S$1*C9+(1-$S$1)*O9) -> 353.47365 | P10: =($S$2*C9+(1-$S$2)*P9) -> 81.838518 | Q10: =($S$3*C9+(1-$S$3)*Q9) -> 13.976562 | V10: =ABS(C10-O10) -> 353.47365 | W10: =ABS(C10-P10) -> 81.838518 | X10: =ABS(C10-Q10) -> 13.976562
A11: 40217 | B11: 0 | C11: 0 | D11: 547 | E11: 51 | F11: 512 | G11: 0 | H11: 0 | I11: 68 | J11: 314 | K11: 213 | L11: =AVERAGE(C8:C10) -> 1 | M11: =(C11-L11) -> -1 | N11: =ABS(M11) -> 1 | O11: =($S$1*C10+(1-$S$1)*O10) -> 318.12629 | P11: =($S$2*C10+(1-$S$2)*P10) -> 57.286963 | Q11: =($S$3*C10+(1-$S$3)*Q10) -> 6.9882812 | V11: =ABS(C11-O11) -> 318.12629 | W11: =ABS(C11-P11) -> 57.286963 | X11: =ABS(C11-Q11) -> 6.9882812
A12: 40224 | B12: 0 | C12: 0 | D12: 1014 | E12: 159 | F12: 587 | G12: 0 | H12: 1 | I12: 19 | J12: 720 | K12: 442 | L12: =AVERAGE(C9:C11) -> 0 | M12: =(C12-L12) -> 0 | N12: =ABS(M12) -> 0 | O12: =($S$1*C11+(1-$S$1)*O11) -> 286.31366 | P12: =($S$2*C11+(1-$S$2)*P11) -> 40.100874 | Q12: =($S$3*C11+(1-$S$3)*Q11) -> 3.4941406 | V12: =ABS(C12-O12) -> 286.31366 | W12: =ABS(C12-P12) -> 40.100874 | X12: =ABS(C12-Q12) -> 3.4941406
A13: 40231 | B13: 0 | C13: 0 | D13: 613 | E13: 79 | F13: 294 | G13: 0 | H13: 0 | I13: 1407 | J13: 551 | K13: 272 | L13: =AVERAGE(C10:C12) -> 0 | M13: =(C13-L13) -> 0 | N13: =ABS(M13) -> 0 | O13: =($S$1*C12+(1-$S$1)*O12) -> 257.68229 | P13: =($S$2*C12+(1-$S$2)*P12) -> 28.070612 | Q13: =($S$3*C12+(1-$S$3)*Q12) -> 1.7470703 | V13: =ABS(C13-O13) -> 257.68229 | W13: =ABS(C13-P13) -> 28.070612 | X13: =ABS(C13-Q13) -> 1.7470703
A14: 40238 | B14: 0 | C14: 3 | D14: 754 | E14: 78 | F14: 735 | G14: 3 | H14: 2 | I14: 133 | J14: 306 | K14: 409 | L14: =AVERAGE(C11:C13) -> 0 | M14: =(C14-L14) -> 3 | N14: =ABS(M14) -> 3 | O14: =($S$1*C13+(1-$S$1)*O13) -> 231.91406 | P14: =($S$2*C13+(1-$S$2)*P13) -> 19.649428 | Q14: =($S$3*C13+(1-$S$3)*Q13) -> 0.87353516 | V14: =ABS(C14-O14) -> 228.91406 | W14: =ABS(C14-P14) -> 16.649428 | X14: =ABS(C14-Q14) -> 2.1264648
A15: 40245 | B15: 0 | C15: 0 | D15: 800 | E15: 262 | F15: 917 | G15: 0 | H15: 0 | I15: 47 | J15: 405 | K15: 337 | L15: =AVERAGE(C12:C14) -> 1 | M15: =(C15-L15) -> -1 | N15: =ABS(M15) -> 1 | O15: =($S$1*C14+(1-$S$1)*O14) -> 209.02266 | P15: =($S$2*C14+(1-$S$2)*P14) -> 14.6546 | Q15: =($S$3*C14+(1-$S$3)*Q14) -> 1.9367676 | V15: =ABS(C15-O15) -> 209.02266 | W15: =ABS(C15-P15) -> 14.6546 | X15: =ABS(C15-Q15) -> 1.9367676
A16: 40252 | B16: 194 | C16: 12 | D16: 555 | E16: 224 | F16: 551 | G16: 12 | H16: 0 | I16: 826 | J16: 179 | K16: 375 | L16: =AVERAGE(C13:C15) -> 1 | M16: =(C16-L16) -> 11 | N16: =ABS(M16) -> 11 | O16: =($S$1*C15+(1-$S$1)*O15) -> 188.12039 | P16: =($S$2*C15+(1-$S$2)*P15) -> 10.25822 | Q16: =($S$3*C15+(1-$S$3)*Q15) -> 0.96838379 | V16: =ABS(C16-O16) -> 176.12039 | W16: =ABS(C16-P16) -> 1.7417802 | X16: =ABS(C16-Q16) -> 11.031616
... A105: 40875 | B105: 226 | C105: 1564 | D105: 1040 | E105: 105 | F105: 953 | G105: 1564 | H105: 314 | I105: 3275 | J105: 436 | K105: 331 | L105: =AVERAGE(C102:C104) -> 1763 | M105: =(C105-L105) -> -199 | N105: =ABS(M105) -> 199 | O105: =($S$1*C104+(1-$S$1)*O104) -> 878.01448 | P105: =($S$2*C104+(1-$S$2)*P104) -> 1509.1684 | Q105: =($S$3*C104+(1-$S$3)*Q104) -> 1718.043 | V105: =ABS(C105-O105) -> 685.98552 | W105: =ABS(C105-P105) -> 54.83161 | X105: =ABS(C105-Q105) -> 154.04299
T106: MAD _M3 | U106: =AVERAGE(N94:N105) -> 343
T107: MAD _ES_0.1 | U107: =AVERAGE(V94:V105) -> 683.78174
T108: MAD _ES_0.3 | U108: =AVERAGE(W94:W105) -> 375.19523
T109: MAD _ES_0.5 | U109: =AVERAGE(X94:X105) -> 301.583
V111: AVERAGE | W111: STD DEV
V112: =AVERAGE(C2:C105) -> 299.125 | W112: =STDEV(C2:C105) -> 522.80013

Sheet PARTY BUNTING
A1: Week_start | B1: 22423 REGENCY CAKESTAND 3 TI | C1: 85123A WHITE HANGING HEART T- | D1: 85099B JUMBO BAG RED RETROSPO | E1: 47566 PARTY BUNTING | F1: 84879 ASSORTED COLOUR BIRD O | G1: 22086 PAPER CHAIN KIT 50'S C | H1: 79321 CHILLI LIGHTS | I1: 22197 SMALL POPCORN HOLDER | J1: 22386 JUMBO BAG PINK POLKADO | K1: 20725 LUNCH BAG RED RETROSPO | L1: MA3_FORECAST | M1: ERROR | N1: ABS ERROR | O1: ES_0.1 | P1: ES_0.3 | Q1: ES_0.5 | R1: ALPHA | S1: 0.1 | V1: ABSERR_0.1 | W1: ABSERR_0.3 | X1: ABSERR_0.5
A2: 40154 | B2: 0 | C2: 19 | D2: 1233 | E2: 19 | F2: 1213 | G2: 663 | H2: 175 | I2: 153 | J2: 0 | K2: 324 | O2: =(C2) -> 19 | P2: =(C2) -> 19 | Q2: =(C2) -> 19 | S2: 0.3
A3: 40161 | B3: 0 | C3: 52 | D3: 1304 | E3: 52 | F3: 1324 | G3: 572 | H3: 173 | I3: 644 | J3: 0 | K3: 236 | O3: =($S$1*C2+(1-$S$1)*O2) -> 19 | P3: =($S$2*C2+(1-$S$2)*P2) -> 19 | Q3: =($S$3*C2+(1-$S$3)*Q2) -> 19 | S3: 0.5 | V3: =ABS(C3-O3) -> 33 | W3: =ABS(C3-P3) -> 33 | X3: =ABS(C3-Q3) -> 33
A4: 40168 | B4: 0 | C4: 1 | D4: 36 | E4: 1 | F4: 82 | G4: 69 | H4: 19 | I4: 2 | J4: 0 | K4: 111 | O4: =($S$1*C3+(1-$S$1)*O3) -> 22.3 | P4: =($S$2*C3+(1-$S$2)*P3) -> 28.9 | Q4: =($S$3*C3+(1-$S$3)*Q3) -> 35.5 | V4: =ABS(C4-O4) -> 21.3 | W4: =ABS(C4-P4) -> 27.9 | X4: =ABS(C4-Q4) -> 34.5
A5: 40175 | B5: 0 | C5: 0 | D5: 0 | E5: 0 | F5: 0 | G5: 0 | H5: 0 | I5: 0 | J5: 0 | K5: 0 | L5: =AVERAGE(C2:C4) -> 24 | M5: =(C5-L5) -> -24 | N5: =ABS(M5) -> 24 | O5: =($S$1*C4+(1-$S$1)*O4) -> 20.17 | P5: =($S$2*C4+(1-$S$2)*P4) -> 20.53 | Q5: =($S$3*C4+(1-$S$3)*Q4) -> 18.25 | V5: =ABS(C5-O5) -> 20.17 | W5: =ABS(C5-P5) -> 20.53 | X5: =ABS(C5-Q5) -> 18.25
A6: 40182 | B6: 0 | C6: 47 | D6: 1152 | E6: 47 | F6: 168 | G6: 0 | H6: 17 | I6: 21 | J6: 0 | K6: 324 | L6: =AVERAGE(C3:C5) -> 17.666667 | M6: =(C6-L6) -> 29.333333 | N6: =ABS(M6) -> 29.333333 | O6: =($S$1*C5+(1-$S$1)*O5) -> 18.153 | P6: =($S$2*C5+(1-$S$2)*P5) -> 14.371 | Q6: =($S$3*C5+(1-$S$3)*Q5) -> 9.125 | V6: =ABS(C6-O6) -> 28.847 | W6: =ABS(C6-P6) -> 32.629 | X6: =ABS(C6-Q6) -> 37.875
A7: 40189 | B7: 0 | C7: 64 | D7: 928 | E7: 64 | F7: 233 | G7: 20 | H7: 23 | I7: 72 | J7: 0 | K7: 190 | L7: =AVERAGE(C4:C6) -> 16 | M7: =(C7-L7) -> 48 | N7: =ABS(M7) -> 48 | O7: =($S$1*C6+(1-$S$1)*O6) -> 21.0377 | P7: =($S$2*C6+(1-$S$2)*P6) -> 24.1597 | Q7: =($S$3*C6+(1-$S$3)*Q6) -> 28.0625 | V7: =ABS(C7-O7) -> 42.9623 | W7: =ABS(C7-P7) -> 39.8403 | X7: =ABS(C7-Q7) -> 35.9375
A8: 40196 | B8: 0 | C8: 49 | D8: 627 | E8: 49 | F8: 897 | G8: 3 | H8: 0 | I8: 23 | J8: 0 | K8: 479 | L8: =AVERAGE(C5:C7) -> 37 | M8: =(C8-L8) -> 12 | N8: =ABS(M8) -> 12 | O8: =($S$1*C7+(1-$S$1)*O7) -> 25.33393 | P8: =($S$2*C7+(1-$S$2)*P7) -> 36.11179 | Q8: =($S$3*C7+(1-$S$3)*Q7) -> 46.03125 | V8: =ABS(C8-O8) -> 23.66607 | W8: =ABS(C8-P8) -> 12.88821 | X8: =ABS(C8-Q8) -> 2.96875
A9: 40203 | B9: 0 | C9: 186 | D9: 864 | E9: 186 | F9: 211 | G9: 0 | H9: 0 | I9: 621 | J9: 114 | K9: 504 | L9: =AVERAGE(C6:C8) -> 53.333333 | M9: =(C9-L9) -> 132.66667 | N9: =ABS(M9) -> 132.66667 | O9: =($S$1*C8+(1-$S$1)*O8) -> 27.700537 | P9: =($S$2*C8+(1-$S$2)*P8) -> 39.978253 | Q9: =($S$3*C8+(1-$S$3)*Q8) -> 47.515625 | V9: =ABS(C9-O9) -> 158.29946 | W9: =ABS(C9-P9) -> 146.02175 | X9: =ABS(C9-Q9) -> 138.48438
A10: 40210 | B10: 0 | C10: 53 | D10: 488 | E10: 53 | F10: 274 | G10: 0 | H10: 24 | I10: 81 | J10: 338 | K10: 326 | L10: =AVERAGE(C7:C9) -> 99.666667 | M10: =(C10-L10) -> -46.666667 | N10: =ABS(M10) -> 46.666667 | O10: =($S$1*C9+(1-$S$1)*O9) -> 43.530483 | P10: =($S$2*C9+(1-$S$2)*P9) -> 83.784777 | Q10: =($S$3*C9+(1-$S$3)*Q9) -> 116.75781 | V10: =ABS(C10-O10) -> 9.4695167 | W10: =ABS(C10-P10) -> 30.784777 | X10: =ABS(C10-Q10) -> 63.757812
A11: 40217 | B11: 0 | C11: 51 | D11: 547 | E11: 51 | F11: 512 | G11: 0 | H11: 0 | I11: 68 | J11: 314 | K11: 213 | L11: =AVERAGE(C8:C10) -> 96 | M11: =(C11-L11) -> -45 | N11: =ABS(M11) -> 45 | O11: =($S$1*C10+(1-$S$1)*O10) -> 44.477435 | P11: =($S$2*C10+(1-$S$2)*P10) -> 74.549344 | Q11: =($S$3*C10+(1-$S$3)*Q10) -> 84.878906 | V11: =ABS(C11-O11) -> 6.522565 | W11: =ABS(C11-P11) -> 23.549344 | X11: =ABS(C11-Q11) -> 33.878906
A12: 40224 | B12: 0 | C12: 159 | D12: 1014 | E12: 159 | F12: 587 | G12: 0 | H12: 1 | I12: 19 | J12: 720 | K12: 442 | L12: =AVERAGE(C9:C11) -> 96.666667 | M12: =(C12-L12) -> 62.333333 | N12: =ABS(M12) -> 62.333333 | O12: =($S$1*C11+(1-$S$1)*O11) -> 45.129691 | P12: =($S$2*C11+(1-$S$2)*P11) -> 67.484541 | Q12: =($S$3*C11+(1-$S$3)*Q11) -> 67.939453 | V12: =ABS(C12-O12) -> 113.87031 | W12: =ABS(C12-P12) -> 91.515459 | X12: =ABS(C12-Q12) -> 91.060547
A13: 40231 | B13: 0 | C13: 79 | D13: 613 | E13: 79 | F13: 294 | G13: 0 | H13: 0 | I13: 1407 | J13: 551 | K13: 272 | L13: =AVERAGE(C10:C12) -> 87.666667 | M13: =(C13-L13) -> -8.6666667 | N13: =ABS(M13) -> 8.6666667 | O13: =($S$1*C12+(1-$S$1)*O12) -> 56.516722 | P13: =($S$2*C12+(1-$S$2)*P12) -> 94.939179 | Q13: =($S$3*C12+(1-$S$3)*Q12) -> 113.46973 | V13: =ABS(C13-O13) -> 22.483278 | W13: =ABS(C13-P13) -> 15.939179 | X13: =ABS(C13-Q13) -> 34.469727
A14: 40238 | B14: 0 | C14: 78 | D14: 754 | E14: 78 | F14: 735 | G14: 3 | H14: 2 | I14: 133 | J14: 306 | K14: 409 | L14: =AVERAGE(C11:C13) -> 96.333333 | M14: =(C14-L14) -> -18.333333 | N14: =ABS(M14) -> 18.333333 | O14: =($S$1*C13+(1-$S$1)*O13) -> 58.76505 | P14: =($S$2*C13+(1-$S$2)*P13) -> 90.157425 | Q14: =($S$3*C13+(1-$S$3)*Q13) -> 96.234863 | V14: =ABS(C14-O14) -> 19.23495 | W14: =ABS(C14-P14) -> 12.157425 | X14: =ABS(C14-Q14) -> 18.234863
A15: 40245 | B15: 0 | C15: 262 | D15: 800 | E15: 262 | F15: 917 | G15: 0 | H15: 0 | I15: 47 | J15: 405 | K15: 337 | L15: =AVERAGE(C12:C14) -> 105.33333 | M15: =(C15-L15) -> 156.66667 | N15: =ABS(M15) -> 156.66667 | O15: =($S$1*C14+(1-$S$1)*O14) -> 60.688545 | P15: =($S$2*C14+(1-$S$2)*P14) -> 86.510197 | Q15: =($S$3*C14+(1-$S$3)*Q14) -> 87.117432 | V15: =ABS(C15-O15) -> 201.31145 | W15: =ABS(C15-P15) -> 175.4898 | X15: =ABS(C15-Q15) -> 174.88257
A16: 40252 | B16: 194 | C16: 224 | D16: 555 | E16: 224 | F16: 551 | G16: 12 | H16: 0 | I16: 826 | J16: 179 | K16: 375 | L16: =AVERAGE(C13:C15) -> 139.66667 | M16: =(C16-L16) -> 84.333333 | N16: =ABS(M16) -> 84.333333 | O16: =($S$1*C15+(1-$S$1)*O15) -> 80.819691 | P16: =($S$2*C15+(1-$S$2)*P15) -> 139.15714 | Q16: =($S$3*C15+(1-$S$3)*Q15) -> 174.55872 | V16: =ABS(C16-O16) -> 143.18031 | W16: =ABS(C16-P16) -> 84.842862 | X16: =ABS(C16-Q16) -> 49.441284
... A105: 40875 | B105: 226 | C105: 105 | D105: 1040 | E105: 105 | F105: 953 | G105: 1564 | H105: 314 | I105: 3275 | J105: 436 | K105: 331 | L105: =AVERAGE(C102:C104) -> 269.33333 | M105: =(C105-L105) -> -164.33333 | N105: =ABS(M105) -> 164.33333 | O105: =($S$1*C104+(1-$S$1)*O104) -> 283.82238 | P105: =($S$2*C104+(1-$S$2)*P104) -> 252.5748 | Q105: =($S$3*C104+(1-$S$3)*Q104) -> 313.40462 | V105: =ABS(C105-O105) -> 178.82238 | W105: =ABS(C105-P105) -> 147.5748 | X105: =ABS(C105-Q105) -> 208.40462
T106: MAD _M3 | U106: =AVERAGE(N94:N105) -> 88.527778
T107: MAD _ES_0.1 | U107: =AVERAGE(V94:V105) -> 186.1182
T108: MAD _ES_0.3 | U108: =AVERAGE(W94:W105) -> 103.76876
T109: MAD _ES_0.5 | U109: =AVERAGE(X94:X105) -> 95.872906
V111: AVERAGE | W111: STD DEV
V112: =AVERAGE(C2:C105) -> 268.28846 | W112: =STDEV(C2:C105) -> 240.7891

Sheet BIRD ORNAMENT
A1: Week_start | B1: 22423 REGENCY CAKESTAND 3 TI | C1: 85123A WHITE HANGING HEART T- | D1: 85099B JUMBO BAG RED RETROSPO | E1: 47566 PARTY BUNTING | F1: 84879 ASSORTED COLOUR BIRD O | G1: 22086 PAPER CHAIN KIT 50'S C | H1: 79321 CHILLI LIGHTS | I1: 22197 SMALL POPCORN HOLDER | J1: 22386 JUMBO BAG PINK POLKADO | K1: 20725 LUNCH BAG RED RETROSPO | L1: MA3_FORECAST | M1: ERROR | N1: ABS ERROR | O1: ES_0.1 | P1: ES_0.3 | Q1: ES_0.5 | R1: ALPHA | S1: 0.1 | V1: ABSERR_0.1 | W1: ABSERR_0.3 | X1: ABSERR_0.5
A2: 40154 | B2: 0 | C2: 1213 | D2: 1233 | E2: 19 | F2: 1213 | G2: 663 | H2: 175 | I2: 153 | J2: 0 | K2: 324 | O2: =(C2) -> 1213 | P2: =(C2) -> 1213 | Q2: =(C2) -> 1213 | S2: 0.3
A3: 40161 | B3: 0 | C3: 1324 | D3: 1304 | E3: 52 | F3: 1324 | G3: 572 | H3: 173 | I3: 644 | J3: 0 | K3: 236 | O3: =($S$1*C2+(1-$S$1)*O2) -> 1213 | P3: =($S$2*C2+(1-$S$2)*P2) -> 1213 | Q3: =($S$3*C2+(1-$S$3)*Q2) -> 1213 | S3: 0.5 | V3: =ABS(C3-O3) -> 111 | W3: =ABS(C3-P3) -> 111 | X3: =ABS(C3-Q3) -> 111
A4: 40168 | B4: 0 | C4: 82 | D4: 36 | E4: 1 | F4: 82 | G4: 69 | H4: 19 | I4: 2 | J4: 0 | K4: 111 | O4: =($S$1*C3+(1-$S$1)*O3) -> 1224.1 | P4: =($S$2*C3+(1-$S$2)*P3) -> 1246.3 | Q4: =($S$3*C3+(1-$S$3)*Q3) -> 1268.5 | V4: =ABS(C4-O4) -> 1142.1 | W4: =ABS(C4-P4) -> 1164.3 | X4: =ABS(C4-Q4) -> 1186.5
A5: 40175 | B5: 0 | C5: 0 | D5: 0 | E5: 0 | F5: 0 | G5: 0 | H5: 0 | I5: 0 | J5: 0 | K5: 0 | L5: =AVERAGE(C2:C4) -> 873 | M5: =(C5-L5) -> -873 | N5: =ABS(M5) -> 873 | O5: =($S$1*C4+(1-$S$1)*O4) -> 1109.89 | P5: =($S$2*C4+(1-$S$2)*P4) -> 897.01 | Q5: =($S$3*C4+(1-$S$3)*Q4) -> 675.25 | V5: =ABS(C5-O5) -> 1109.89 | W5: =ABS(C5-P5) -> 897.01 | X5: =ABS(C5-Q5) -> 675.25
A6: 40182 | B6: 0 | C6: 168 | D6: 1152 | E6: 47 | F6: 168 | G6: 0 | H6: 17 | I6: 21 | J6: 0 | K6: 324 | L6: =AVERAGE(C3:C5) -> 468.66667 | M6: =(C6-L6) -> -300.66667 | N6: =ABS(M6) -> 300.66667 | O6: =($S$1*C5+(1-$S$1)*O5) -> 998.901 | P6: =($S$2*C5+(1-$S$2)*P5) -> 627.907 | Q6: =($S$3*C5+(1-$S$3)*Q5) -> 337.625 | V6: =ABS(C6-O6) -> 830.901 | W6: =ABS(C6-P6) -> 459.907 | X6: =ABS(C6-Q6) -> 169.625
A7: 40189 | B7: 0 | C7: 233 | D7: 928 | E7: 64 | F7: 233 | G7: 20 | H7: 23 | I7: 72 | J7: 0 | K7: 190 | L7: =AVERAGE(C4:C6) -> 83.333333 | M7: =(C7-L7) -> 149.66667 | N7: =ABS(M7) -> 149.66667 | O7: =($S$1*C6+(1-$S$1)*O6) -> 915.8109 | P7: =($S$2*C6+(1-$S$2)*P6) -> 489.9349 | Q7: =($S$3*C6+(1-$S$3)*Q6) -> 252.8125 | V7: =ABS(C7-O7) -> 682.8109 | W7: =ABS(C7-P7) -> 256.9349 | X7: =ABS(C7-Q7) -> 19.8125
A8: 40196 | B8: 0 | C8: 897 | D8: 627 | E8: 49 | F8: 897 | G8: 3 | H8: 0 | I8: 23 | J8: 0 | K8: 479 | L8: =AVERAGE(C5:C7) -> 133.66667 | M8: =(C8-L8) -> 763.33333 | N8: =ABS(M8) -> 763.33333 | O8: =($S$1*C7+(1-$S$1)*O7) -> 847.52981 | P8: =($S$2*C7+(1-$S$2)*P7) -> 412.85443 | Q8: =($S$3*C7+(1-$S$3)*Q7) -> 242.90625 | V8: =ABS(C8-O8) -> 49.47019 | W8: =ABS(C8-P8) -> 484.14557 | X8: =ABS(C8-Q8) -> 654.09375
A9: 40203 | B9: 0 | C9: 211 | D9: 864 | E9: 186 | F9: 211 | G9: 0 | H9: 0 | I9: 621 | J9: 114 | K9: 504 | L9: =AVERAGE(C6:C8) -> 432.66667 | M9: =(C9-L9) -> -221.66667 | N9: =ABS(M9) -> 221.66667 | O9: =($S$1*C8+(1-$S$1)*O8) -> 852.47683 | P9: =($S$2*C8+(1-$S$2)*P8) -> 558.0981 | Q9: =($S$3*C8+(1-$S$3)*Q8) -> 569.95312 | V9: =ABS(C9-O9) -> 641.47683 | W9: =ABS(C9-P9) -> 347.0981 | X9: =ABS(C9-Q9) -> 358.95312
A10: 40210 | B10: 0 | C10: 274 | D10: 488 | E10: 53 | F10: 274 | G10: 0 | H10: 24 | I10: 81 | J10: 338 | K10: 326 | L10: =AVERAGE(C7:C9) -> 447 | M10: =(C10-L10) -> -173 | N10: =ABS(M10) -> 173 | O10: =($S$1*C9+(1-$S$1)*O9) -> 788.32915 | P10: =($S$2*C9+(1-$S$2)*P9) -> 453.96867 | Q10: =($S$3*C9+(1-$S$3)*Q9) -> 390.47656 | V10: =ABS(C10-O10) -> 514.32915 | W10: =ABS(C10-P10) -> 179.96867 | X10: =ABS(C10-Q10) -> 116.47656
A11: 40217 | B11: 0 | C11: 512 | D11: 547 | E11: 51 | F11: 512 | G11: 0 | H11: 0 | I11: 68 | J11: 314 | K11: 213 | L11: =AVERAGE(C8:C10) -> 460.66667 | M11: =(C11-L11) -> 51.333333 | N11: =ABS(M11) -> 51.333333 | O11: =($S$1*C10+(1-$S$1)*O10) -> 736.89623 | P11: =($S$2*C10+(1-$S$2)*P10) -> 399.97807 | Q11: =($S$3*C10+(1-$S$3)*Q10) -> 332.23828 | V11: =ABS(C11-O11) -> 224.89623 | W11: =ABS(C11-P11) -> 112.02193 | X11: =ABS(C11-Q11) -> 179.76172
A12: 40224 | B12: 0 | C12: 587 | D12: 1014 | E12: 159 | F12: 587 | G12: 0 | H12: 1 | I12: 19 | J12: 720 | K12: 442 | L12: =AVERAGE(C9:C11) -> 332.33333 | M12: =(C12-L12) -> 254.66667 | N12: =ABS(M12) -> 254.66667 | O12: =($S$1*C11+(1-$S$1)*O11) -> 714.40661 | P12: =($S$2*C11+(1-$S$2)*P11) -> 433.58465 | Q12: =($S$3*C11+(1-$S$3)*Q11) -> 422.11914 | V12: =ABS(C12-O12) -> 127.40661 | W12: =ABS(C12-P12) -> 153.41535 | X12: =ABS(C12-Q12) -> 164.88086
A13: 40231 | B13: 0 | C13: 294 | D13: 613 | E13: 79 | F13: 294 | G13: 0 | H13: 0 | I13: 1407 | J13: 551 | K13: 272 | L13: =AVERAGE(C10:C12) -> 457.66667 | M13: =(C13-L13) -> -163.66667 | N13: =ABS(M13) -> 163.66667 | O13: =($S$1*C12+(1-$S$1)*O12) -> 701.66595 | P13: =($S$2*C12+(1-$S$2)*P12) -> 479.60925 | Q13: =($S$3*C12+(1-$S$3)*Q12) -> 504.55957 | V13: =ABS(C13-O13) -> 407.66595 | W13: =ABS(C13-P13) -> 185.60925 | X13: =ABS(C13-Q13) -> 210.55957
A14: 40238 | B14: 0 | C14: 735 | D14: 754 | E14: 78 | F14: 735 | G14: 3 | H14: 2 | I14: 133 | J14: 306 | K14: 409 | L14: =AVERAGE(C11:C13) -> 464.33333 | M14: =(C14-L14) -> 270.66667 | N14: =ABS(M14) -> 270.66667 | O14: =($S$1*C13+(1-$S$1)*O13) -> 660.89935 | P14: =($S$2*C13+(1-$S$2)*P13) -> 423.92648 | Q14: =($S$3*C13+(1-$S$3)*Q13) -> 399.27979 | V14: =ABS(C14-O14) -> 74.100647 | W14: =ABS(C14-P14) -> 311.07352 | X14: =ABS(C14-Q14) -> 335.72021
A15: 40245 | B15: 0 | C15: 917 | D15: 800 | E15: 262 | F15: 917 | G15: 0 | H15: 0 | I15: 47 | J15: 405 | K15: 337 | L15: =AVERAGE(C12:C14) -> 538.66667 | M15: =(C15-L15) -> 378.33333 | N15: =ABS(M15) -> 378.33333 | O15: =($S$1*C14+(1-$S$1)*O14) -> 668.30942 | P15: =($S$2*C14+(1-$S$2)*P14) -> 517.24853 | Q15: =($S$3*C14+(1-$S$3)*Q14) -> 567.13989 | V15: =ABS(C15-O15) -> 248.69058 | W15: =ABS(C15-P15) -> 399.75147 | X15: =ABS(C15-Q15) -> 349.86011
A16: 40252 | B16: 194 | C16: 551 | D16: 555 | E16: 224 | F16: 551 | G16: 12 | H16: 0 | I16: 826 | J16: 179 | K16: 375 | L16: =AVERAGE(C13:C15) -> 648.66667 | M16: =(C16-L16) -> -97.666667 | N16: =ABS(M16) -> 97.666667 | O16: =($S$1*C15+(1-$S$1)*O15) -> 693.17848 | P16: =($S$2*C15+(1-$S$2)*P15) -> 637.17397 | Q16: =($S$3*C15+(1-$S$3)*Q15) -> 742.06995 | V16: =ABS(C16-O16) -> 142.17848 | W16: =ABS(C16-P16) -> 86.173974 | X16: =ABS(C16-Q16) -> 191.06995
... A105: 40875 | B105: 226 | C105: 953 | D105: 1040 | E105: 105 | F105: 953 | G105: 1564 | H105: 314 | I105: 3275 | J105: 436 | K105: 331 | L105: =AVERAGE(C102:C104) -> 1370.3333 | M105: =(C105-L105) -> -417.33333 | N105: =ABS(M105) -> 417.33333 | O105: =($S$1*C104+(1-$S$1)*O104) -> 914.9855 | P105: =($S$2*C104+(1-$S$2)*P104) -> 1117.1485 | Q105: =($S$3*C104+(1-$S$3)*Q104) -> 1174.7798 | V105: =ABS(C105-O105) -> 38.014505 | W105: =ABS(C105-P105) -> 164.14851 | X105: =ABS(C105-Q105) -> 221.77977
T106: MAD _M3 | U106: =AVERAGE(N94:N105) -> 297.86111
T107: MAD _ES_0.1 | U107: =AVERAGE(V94:V105) -> 235.73432
T108: MAD _ES_0.3 | U108: =AVERAGE(W94:W105) -> 237.35175
T109: MAD _ES_0.5 | U109: =AVERAGE(X94:X105) -> 246.02942
V111: AVERAGE | W111: STD DEV
V112: =AVERAGE(C2:C105) -> 741.80769 | W112: =STDEV(C2:C105) -> 694.77212

Sheet JUMBO RED BAG
A1: Week_start | B1: 22423 REGENCY CAKESTAND 3 TI | C1: 85123A WHITE HANGING HEART T- | D1: 85099B JUMBO BAG RED RETROSPO | E1: 47566 PARTY BUNTING | F1: 84879 ASSORTED COLOUR BIRD O | G1: 22086 PAPER CHAIN KIT 50'S C | H1: 79321 CHILLI LIGHTS | I1: 22197 SMALL POPCORN HOLDER | J1: 22386 JUMBO BAG PINK POLKADO | K1: 20725 LUNCH BAG RED RETROSPO | L1: MA3_FORECAST | M1: ERROR | N1: ABS ERROR | O1: ES_0.1 | P1: ES_0.3 | Q1: ES_0.5 | R1: ALPHA | S1: 0.1 | V1: ABSERR_0.1 | W1: ABSERR_0.3 | X1: ABSERR_0.5
A2: 40154 | B2: 0 | C2: 1233 | D2: 1233 | E2: 19 | F2: 1213 | G2: 663 | H2: 175 | I2: 153 | J2: 0 | K2: 324 | O2: =(C2) -> 1233 | P2: =(C2) -> 1233 | Q2: =(C2) -> 1233 | S2: 0.3
A3: 40161 | B3: 0 | C3: 1304 | D3: 1304 | E3: 52 | F3: 1324 | G3: 572 | H3: 173 | I3: 644 | J3: 0 | K3: 236 | O3: =($S$1*C2+(1-$S$1)*O2) -> 1233 | P3: =($S$2*C2+(1-$S$2)*P2) -> 1233 | Q3: =($S$3*C2+(1-$S$3)*Q2) -> 1233 | S3: 0.5 | V3: =ABS(C3-O3) -> 71 | W3: =ABS(C3-P3) -> 71 | X3: =ABS(C3-Q3) -> 71
A4: 40168 | B4: 0 | C4: 36 | D4: 36 | E4: 1 | F4: 82 | G4: 69 | H4: 19 | I4: 2 | J4: 0 | K4: 111 | O4: =($S$1*C3+(1-$S$1)*O3) -> 1240.1 | P4: =($S$2*C3+(1-$S$2)*P3) -> 1254.3 | Q4: =($S$3*C3+(1-$S$3)*Q3) -> 1268.5 | V4: =ABS(C4-O4) -> 1204.1 | W4: =ABS(C4-P4) -> 1218.3 | X4: =ABS(C4-Q4) -> 1232.5
A5: 40175 | B5: 0 | C5: 0 | D5: 0 | E5: 0 | F5: 0 | G5: 0 | H5: 0 | I5: 0 | J5: 0 | K5: 0 | L5: =AVERAGE(C2:C4) -> 857.66667 | M5: =(C5-L5) -> -857.66667 | N5: =ABS(M5) -> 857.66667 | O5: =($S$1*C4+(1-$S$1)*O4) -> 1119.69 | P5: =($S$2*C4+(1-$S$2)*P4) -> 888.81 | Q5: =($S$3*C4+(1-$S$3)*Q4) -> 652.25 | V5: =ABS(C5-O5) -> 1119.69 | W5: =ABS(C5-P5) -> 888.81 | X5: =ABS(C5-Q5) -> 652.25
A6: 40182 | B6: 0 | C6: 1152 | D6: 1152 | E6: 47 | F6: 168 | G6: 0 | H6: 17 | I6: 21 | J6: 0 | K6: 324 | L6: =AVERAGE(C3:C5) -> 446.66667 | M6: =(C6-L6) -> 705.33333 | N6: =ABS(M6) -> 705.33333 | O6: =($S$1*C5+(1-$S$1)*O5) -> 1007.721 | P6: =($S$2*C5+(1-$S$2)*P5) -> 622.167 | Q6: =($S$3*C5+(1-$S$3)*Q5) -> 326.125 | V6: =ABS(C6-O6) -> 144.279 | W6: =ABS(C6-P6) -> 529.833 | X6: =ABS(C6-Q6) -> 825.875
A7: 40189 | B7: 0 | C7: 928 | D7: 928 | E7: 64 | F7: 233 | G7: 20 | H7: 23 | I7: 72 | J7: 0 | K7: 190 | L7: =AVERAGE(C4:C6) -> 396 | M7: =(C7-L7) -> 532 | N7: =ABS(M7) -> 532 | O7: =($S$1*C6+(1-$S$1)*O6) -> 1022.1489 | P7: =($S$2*C6+(1-$S$2)*P6) -> 781.1169 | Q7: =($S$3*C6+(1-$S$3)*Q6) -> 739.0625 | V7: =ABS(C7-O7) -> 94.1489 | W7: =ABS(C7-P7) -> 146.8831 | X7: =ABS(C7-Q7) -> 188.9375
A8: 40196 | B8: 0 | C8: 627 | D8: 627 | E8: 49 | F8: 897 | G8: 3 | H8: 0 | I8: 23 | J8: 0 | K8: 479 | L8: =AVERAGE(C5:C7) -> 693.33333 | M8: =(C8-L8) -> -66.333333 | N8: =ABS(M8) -> 66.333333 | O8: =($S$1*C7+(1-$S$1)*O7) -> 1012.734 | P8: =($S$2*C7+(1-$S$2)*P7) -> 825.18183 | Q8: =($S$3*C7+(1-$S$3)*Q7) -> 833.53125 | V8: =ABS(C8-O8) -> 385.73401 | W8: =ABS(C8-P8) -> 198.18183 | X8: =ABS(C8-Q8) -> 206.53125
A9: 40203 | B9: 0 | C9: 864 | D9: 864 | E9: 186 | F9: 211 | G9: 0 | H9: 0 | I9: 621 | J9: 114 | K9: 504 | L9: =AVERAGE(C6:C8) -> 902.33333 | M9: =(C9-L9) -> -38.333333 | N9: =ABS(M9) -> 38.333333 | O9: =($S$1*C8+(1-$S$1)*O8) -> 974.16061 | P9: =($S$2*C8+(1-$S$2)*P8) -> 765.72728 | Q9: =($S$3*C8+(1-$S$3)*Q8) -> 730.26562 | V9: =ABS(C9-O9) -> 110.16061 | W9: =ABS(C9-P9) -> 98.272719 | X9: =ABS(C9-Q9) -> 133.73438
A10: 40210 | B10: 0 | C10: 488 | D10: 488 | E10: 53 | F10: 274 | G10: 0 | H10: 24 | I10: 81 | J10: 338 | K10: 326 | L10: =AVERAGE(C7:C9) -> 806.33333 | M10: =(C10-L10) -> -318.33333 | N10: =ABS(M10) -> 318.33333 | O10: =($S$1*C9+(1-$S$1)*O9) -> 963.14455 | P10: =($S$2*C9+(1-$S$2)*P9) -> 795.2091 | Q10: =($S$3*C9+(1-$S$3)*Q9) -> 797.13281 | V10: =ABS(C10-O10) -> 475.14455 | W10: =ABS(C10-P10) -> 307.2091 | X10: =ABS(C10-Q10) -> 309.13281
A11: 40217 | B11: 0 | C11: 547 | D11: 547 | E11: 51 | F11: 512 | G11: 0 | H11: 0 | I11: 68 | J11: 314 | K11: 213 | L11: =AVERAGE(C8:C10) -> 659.66667 | M11: =(C11-L11) -> -112.66667 | N11: =ABS(M11) -> 112.66667 | O11: =($S$1*C10+(1-$S$1)*O10) -> 915.63009 | P11: =($S$2*C10+(1-$S$2)*P10) -> 703.04637 | Q11: =($S$3*C10+(1-$S$3)*Q10) -> 642.56641 | V11: =ABS(C11-O11) -> 368.63009 | W11: =ABS(C11-P11) -> 156.04637 | X11: =ABS(C11-Q11) -> 95.566406
A12: 40224 | B12: 0 | C12: 1014 | D12: 1014 | E12: 159 | F12: 587 | G12: 0 | H12: 1 | I12: 19 | J12: 720 | K12: 442 | L12: =AVERAGE(C9:C11) -> 633 | M12: =(C12-L12) -> 381 | N12: =ABS(M12) -> 381 | O12: =($S$1*C11+(1-$S$1)*O11) -> 878.76708 | P12: =($S$2*C11+(1-$S$2)*P11) -> 656.23246 | Q12: =($S$3*C11+(1-$S$3)*Q11) -> 594.7832 | V12: =ABS(C12-O12) -> 135.23292 | W12: =ABS(C12-P12) -> 357.76754 | X12: =ABS(C12-Q12) -> 419.2168
A13: 40231 | B13: 0 | C13: 613 | D13: 613 | E13: 79 | F13: 294 | G13: 0 | H13: 0 | I13: 1407 | J13: 551 | K13: 272 | L13: =AVERAGE(C10:C12) -> 683 | M13: =(C13-L13) -> -70 | N13: =ABS(M13) -> 70 | O13: =($S$1*C12+(1-$S$1)*O12) -> 892.29038 | P13: =($S$2*C12+(1-$S$2)*P12) -> 763.56272 | Q13: =($S$3*C12+(1-$S$3)*Q12) -> 804.3916 | V13: =ABS(C13-O13) -> 279.29038 | W13: =ABS(C13-P13) -> 150.56272 | X13: =ABS(C13-Q13) -> 191.3916
A14: 40238 | B14: 0 | C14: 754 | D14: 754 | E14: 78 | F14: 735 | G14: 3 | H14: 2 | I14: 133 | J14: 306 | K14: 409 | L14: =AVERAGE(C11:C13) -> 724.66667 | M14: =(C14-L14) -> 29.333333 | N14: =ABS(M14) -> 29.333333 | O14: =($S$1*C13+(1-$S$1)*O13) -> 864.36134 | P14: =($S$2*C13+(1-$S$2)*P13) -> 718.3939 | Q14: =($S$3*C13+(1-$S$3)*Q13) -> 708.6958 | V14: =ABS(C14-O14) -> 110.36134 | W14: =ABS(C14-P14) -> 35.606096 | X14: =ABS(C14-Q14) -> 45.304199
A15: 40245 | B15: 0 | C15: 800 | D15: 800 | E15: 262 | F15: 917 | G15: 0 | H15: 0 | I15: 47 | J15: 405 | K15: 337 | L15: =AVERAGE(C12:C14) -> 793.66667 | M15: =(C15-L15) -> 6.3333333 | N15: =ABS(M15) -> 6.3333333 | O15: =($S$1*C14+(1-$S$1)*O14) -> 853.3252 | P15: =($S$2*C14+(1-$S$2)*P14) -> 729.07573 | Q15: =($S$3*C14+(1-$S$3)*Q14) -> 731.3479 | V15: =ABS(C15-O15) -> 53.325204 | W15: =ABS(C15-P15) -> 70.924267 | X15: =ABS(C15-Q15) -> 68.6521
A16: 40252 | B16: 194 | C16: 555 | D16: 555 | E16: 224 | F16: 551 | G16: 12 | H16: 0 | I16: 826 | J16: 179 | K16: 375 | L16: =AVERAGE(C13:C15) -> 722.33333 | M16: =(C16-L16) -> -167.33333 | N16: =ABS(M16) -> 167.33333 | O16: =($S$1*C15+(1-$S$1)*O15) -> 847.99268 | P16: =($S$2*C15+(1-$S$2)*P15) -> 750.35301 | Q16: =($S$3*C15+(1-$S$3)*Q15) -> 765.67395 | V16: =ABS(C16-O16) -> 292.99268 | W16: =ABS(C16-P16) -> 195.35301 | X16: =ABS(C16-Q16) -> 210.67395
... A105: 40875 | B105: 226 | C105: 1040 | D105: 1040 | E105: 105 | F105: 953 | G105: 1564 | H105: 314 | I105: 3275 | J105: 436 | K105: 331 | L105: =AVERAGE(C102:C104) -> 1485 | M105: =(C105-L105) -> -445 | N105: =ABS(M105) -> 445 | O105: =($S$1*C104+(1-$S$1)*O104) -> 1133.7197 | P105: =($S$2*C104+(1-$S$2)*P104) -> 1215.9888 | Q105: =($S$3*C104+(1-$S$3)*Q104) -> 1157.1764 | V105: =ABS(C105-O105) -> 93.719706 | W105: =ABS(C105-P105) -> 175.98876 | X105: =ABS(C105-Q105) -> 117.17635
T106: MAD _M3 | U106: =AVERAGE(N94:N105) -> 687.83333
T107: MAD _ES_0.1 | U107: =AVERAGE(V94:V105) -> 481.8913
T108: MAD _ES_0.3 | U108: =AVERAGE(W94:W105) -> 558.20344
T109: MAD _ES_0.5 | U109: =AVERAGE(X94:X105) -> 595.81867
V111: AVERAGE | W111: STD DEV
V112: =AVERAGE(C2:C105) -> 907.44231 | W112: =STDEV(C2:C105) -> 473.95743

Sheet ABC ANALYSIS
A1: Rank | B1: StockCode | C1: Description | D1: Median_Price_GBP | E1: Annual_Demand_Units | F1: Annual_Value_GBP | G1: CUMULATIVE_GBP | H1: CUMULATIVE_PCT | I1: CLASS | K1: NO.OF CLASS A | L1: =COUNTIF(I2:I4871,"A") -> 1052
A2: 1 | B2: 22423 | C2: REGENCY CAKESTAND 3 TIER | D2: 12.75 | E2: 12894 | F2: 161353.68 | G2: =F2 -> 161353.68 | H2: =G2/$G$4871 -> 0.016905555 | I2: =IF(H2<=0.8,"A",IF(H2<=0.95,"B","C")) -> A | K2: NO.OF CLASS B | L2: =COUNTIF(I2:I4871,"B") -> 1275
A3: 2 | B3: 85123A | C3: WHITE HANGING HEART T-LIGHT HOLDER | D3: 2.95 | E3: 45480 | F3: 124710.66 | G3: =F3+G2 -> 286064.34 | H3: =G3/$G$4871 -> 0.0299719 | I3: =IF(H3<=0.8,"A",IF(H3<=0.95,"B","C")) -> A | K3: NO.OF CLASS C | L3: =COUNTIF(I2:I4871,"C") -> 2543
A4: 3 | B4: 85099B | C4: JUMBO BAG RED RETROSPOT | D4: 1.95 | E4: 48012 | F4: 89638.4 | G4: =F4+G3 -> 375702.74 | H4: =G4/$G$4871 -> 0.039363609 | I4: =IF(H4<=0.8,"A",IF(H4<=0.95,"B","C")) -> A
A5: 4 | B5: 47566 | C5: PARTY BUNTING | D5: 4.95 | E5: 14008 | F5: 73766.52 | G5: =F5+G4 -> 449469.26 | H5: =G5/$G$4871 -> 0.04709237 | I5: =IF(H5<=0.8,"A",IF(H5<=0.95,"B","C")) -> A
A6: 5 | B6: 84879 | C6: ASSORTED COLOUR BIRD ORNAMENT | D6: 1.69 | E6: 39922 | F6: 64505.05 | G6: =F6+G5 -> 513974.31 | H6: =G6/$G$4871 -> 0.053850775 | I6: =IF(H6<=0.8,"A",IF(H6<=0.95,"B","C")) -> A | K6: ORDER_COST | L6: HOLDING_RATE
A7: 6 | B7: 22086 | C7: PAPER CHAIN KIT 50'S CHRISTMAS | D7: 2.95 | E7: 17330 | F7: 58344.22 | G7: =F7+G6 -> 572318.53 | H7: =G7/$G$4871 -> 0.059963691 | I7: =IF(H7<=0.8,"A",IF(H7<=0.95,"B","C")) -> A | K7: 50 | L7: 0.2
A8: 7 | B8: 79321 | C8: CHILLI LIGHTS | D8: 4.95 | E8: 7906 | F8: 40205.86 | G8: =F8+G7 -> 612524.39 | H8: =G8/$G$4871 -> 0.064176191 | I8: =IF(H8<=0.8,"A",IF(H8<=0.95,"B","C")) -> A
A9: 8 | B9: 22197 | C9: SMALL POPCORN HOLDER | D9: 0.85 | E9: 44152 | F9: 39689.8 | G9: =F9+G8 -> 652214.19 | H9: =G9/$G$4871 -> 0.068334621 | I9: =IF(H9<=0.8,"A",IF(H9<=0.95,"B","C")) -> A | K9: PRODUCT | L9: PRICE | M9: YEARLY DEMAND | N9: H_PER UNIT | O9: EOQ | Q9: AVG_WEEKLY | R9: STD DEV_ WEEKLY | S9: SAFETY_STOCK | T9: REORDER_STOCK
A10: 9 | B10: 22386 | C10: JUMBO BAG PINK POLKADOT | D10: 1.95 | E10: 19506 | F10: 37784.09 | G10: =F10+G9 -> 689998.28 | H10: =G10/$G$4871 -> 0.072293384 | I10: =IF(H10<=0.8,"A",IF(H10<=0.95,"B","C")) -> A | K10: =C2 -> REGENCY CAKESTAND 3 TIER | L10: =D2 -> 12.75 | M10: =E2 -> 12894 | N10: =L10*$L$7 -> 2.55 | O10: =SQRT(2*M10*$K$7/N10) -> 711.08864 | Q10: 244.35577 | R10: 178.33686 | S10: =$L$22*R10*SQRT($K$22) -> 416.14058 | T10: =S10+Q10*$K$22 -> 904.85212
A11: 10 | B11: 20725 | C11: LUNCH BAG RED RETROSPOT | D11: 1.65 | E11: 19968 | F11: 35278 | G11: =F11+G10 -> 725276.28 | H11: =G11/$G$4871 -> 0.075989576 | I11: =IF(H11<=0.8,"A",IF(H11<=0.95,"B","C")) -> A | K11: =C3 -> WHITE HANGING HEART T-LIGHT HOLDER | L11: =D3 -> 2.95 | M11: =E3 -> 45480 | N11: =L11*$L$7 -> 0.59 | O11: =SQRT(2*M11*$K$7/N11) -> 2776.414 | Q11: 850.56731 | R11: 496.45232 | S11: =$L$22*R11*SQRT($K$22) -> 1158.4479 | T11: =S11+Q11*$K$22 -> 2859.5825
A12: 11 | B12: 85099F | C12: JUMBO BAG STRAWBERRY | D12: 1.95 | E12: 18340 | F12: 33838.79 | G12: =F12+G11 -> 759115.07 | H12: =G12/$G$4871 -> 0.079534977 | I12: =IF(H12<=0.8,"A",IF(H12<=0.95,"B","C")) -> A | K12: =C4 -> JUMBO BAG RED RETROSPOT | L12: =D4 -> 1.95 | M12: =E4 -> 48012 | N12: =L12*$L$7 -> 0.39 | O12: =SQRT(2*M12*$K$7/N12) -> 3508.6706 | Q12: 907.44231 | R12: 473.95743 | S12: =$L$22*R12*SQRT($K$22) -> 1105.9571 | T12: =S12+Q12*$K$22 -> 2920.8417
A13: 12 | B13: 48138 | C13: DOORMAT UNION FLAG | D13: 7.49 | E13: 5036 | F13: 33483.12 | G13: =F13+G12 -> 792598.19 | H13: =G13/$G$4871 -> 0.083043114 | I13: =IF(H13<=0.8,"A",IF(H13<=0.95,"B","C")) -> A | K13: =C5 -> PARTY BUNTING | L13: =D5 -> 4.95 | M13: =E5 -> 14008 | N13: =L13*$L$7 -> 0.99 | O13: =SQRT(2*M13*$K$7/N13) -> 1189.5165 | Q13: 268.28846 | R13: 240.7891 | S13: =$L$22*R13*SQRT($K$22) -> 561.8699 | T13: =S13+Q13*$K$22 -> 1098.4468
A14: 13 | B14: 23084 | C14: RABBIT NIGHT LIGHT | D14: 2.08 | E14: 15379 | F14: 33451.3 | G14: =F14+G13 -> 826049.49 | H14: =G14/$G$4871 -> 0.086547916 | I14: =IF(H14<=0.8,"A",IF(H14<=0.95,"B","C")) -> A | K14: =C6 -> ASSORTED COLOUR BIRD ORNAMENT | L14: =D6 -> 1.69 | M14: =E6 -> 39922 | N14: =L14*$L$7 -> 0.338 | O14: =SQRT(2*M14*$K$7/N14) -> 3436.7488 | Q14: 741.80769 | R14: 694.77212 | S14: =$L$22*R14*SQRT($K$22) -> 1621.2176 | T14: =S14+Q14*$K$22 -> 3104.833
A15: 14 | B15: 20685 | C15: DOORMAT RED RETROSPOT | D15: 7.95 | E15: 4850 | F15: 32924.29 | G15: =F15+G14 -> 858973.78 | H15: =G15/$G$4871 -> 0.089997502 | I15: =IF(H15<=0.8,"A",IF(H15<=0.95,"B","C")) -> A | K15: =C7 -> PAPER CHAIN KIT 50'S CHRISTMAS | L15: =D7 -> 2.95 | M15: =E7 -> 17330 | N15: =L15*$L$7 -> 0.59 | O15: =SQRT(2*M15*$K$7/N15) -> 1713.8518 | Q15: 299.125 | R15: 522.80013 | S15: =$L$22*R15*SQRT($K$22) -> 1219.9292 | T15: =S15+Q15*$K$22 -> 1818.1792
A16: 15 | B16: 21137 | C16: BLACK RECORD COVER FRAME | D16: 3.75 | E16: 9368 | F16: 32589.02 | G16: =F16+G15 -> 891562.8 | H16: =G16/$G$4871 -> 0.093411961 | I16: =IF(H16<=0.8,"A",IF(H16<=0.95,"B","C")) -> A | K16: =C8 -> CHILLI LIGHTS | L16: =D8 -> 4.95 | M16: =E8 -> 7906 | N16: =L16*$L$7 -> 0.99 | O16: =SQRT(2*M16*$K$7/N16) -> 893.63631 | Q16: 148.25 | R16: 190.58514 | S16: =$L$22*R16*SQRT($K$22) -> 444.72134 | T16: =S16+Q16*$K$22 -> 741.22134
A17: 16 | B17: 21843 | C17: RED RETROSPOT CAKE STAND | D17: 10.95 | E17: 2914 | F17: 31316.82 | G17: =F17+G16 -> 922879.62 | H17: =G17/$G$4871 -> 0.096693127 | I17: =IF(H17<=0.8,"A",IF(H17<=0.95,"B","C")) -> A | K17: =C9 -> SMALL POPCORN HOLDER | L17: =D9 -> 0.85 | M17: =E9 -> 44152 | N17: =L17*$L$7 -> 0.17 | O17: =SQRT(2*M17*$K$7/N17) -> 5096.2501 | Q17: 799.71154 | R17: 903.03227 | S17: =$L$22*R17*SQRT($K$22) -> 2107.1828 | T17: =S17+Q17*$K$22 -> 3706.6059
A18: 17 | B18: 21931 | C18: JUMBO STORAGE BAG SUKI | D18: 1.95 | E18: 14425 | F18: 30470.99 | G18: =F18+G17 -> 953350.61 | H18: =G18/$G$4871 -> 0.099885672 | I18: =IF(H18<=0.8,"A",IF(H18<=0.95,"B","C")) -> A | K18: =C10 -> JUMBO BAG PINK POLKADOT | L18: =D10 -> 1.95 | M18: =E10 -> 19506 | N18: =L18*$L$7 -> 0.39 | O18: =SQRT(2*M18*$K$7/N18) -> 2236.412 | Q18: 374.125 | R18: 254.29952 | S18: =$L$22*R18*SQRT($K$22) -> 593.39582 | T18: =S18+Q18*$K$22 -> 1341.6458
A19: 18 | B19: 21621 | C19: VINTAGE UNION JACK BUNTING | D19: 8.5 | E19: 3436 | F19: 30024.02 | G19: =F19+G18 -> 983374.63 | H19: =G19/$G$4871 -> 0.10303139 | I19: =IF(H19<=0.8,"A",IF(H19<=0.95,"B","C")) -> A | K19: =C11 -> LUNCH BAG RED RETROSPOT | L19: =D11 -> 1.65 | M19: =E11 -> 19968 | N19: =L19*$L$7 -> 0.33 | O19: =SQRT(2*M19*$K$7/N19) -> 2459.8596 | Q19: 378.50962 | R19: 175.84702 | S19: =$L$22*R19*SQRT($K$22) -> 410.33065 | T19: =S19+Q19*$K$22 -> 1167.3499
A20: 19 | B20: 22114 | C20: HOT WATER BOTTLE TEA AND SYMPATHY | D20: 3.95 | E20: 5778 | F20: 29382.75 | G20: =F20+G19 -> 1012757.4 | H20: =G20/$G$4871 -> 0.10610991 | I20: =IF(H20<=0.8,"A",IF(H20<=0.95,"B","C")) -> A
A21: 20 | B21: 85099C | C21: JUMBO BAG BAROQUE BLACK WHITE | D21: 1.95 | E21: 15218 | F21: 29347.92 | G21: =F21+G20 -> 1042105.3 | H21: =G21/$G$4871 -> 0.10918479 | I21: =IF(H21<=0.8,"A",IF(H21<=0.95,"B","C")) -> A | K21: LEAD TIME_WEEKS | L21: Z VALUE
A22: 21 | B22: 22112 | C22: CHOCOLATE HOT WATER BOTTLE | D22: 4.95 | E22: 5528 | F22: 28979.57 | G22: =F22+G21 -> 1071084.9 | H22: =G22/$G$4871 -> 0.11222108 | I22: =IF(H22<=0.8,"A",IF(H22<=0.95,"B","C")) -> A | K22: 2 | L22: 1.65
A23: 22 | B23: 15056N | C23: EDWARDIAN PARASOL NATURAL | D23: 5.95 | E23: 5626 | F23: 28883.6 | G23: =F23+G22 -> 1099968.5 | H23: =G23/$G$4871 -> 0.11524731 | I23: =IF(H23<=0.8,"A",IF(H23<=0.95,"B","C")) -> A
A24: 23 | B24: 22910 | C24: PAPER CHAIN KIT VINTAGE CHRISTMAS | D24: 2.95 | E24: 9124 | F24: 28822.48 | G24: =F24+G23 -> 1128790.9 | H24: =G24/$G$4871 -> 0.11826713 | I24: =IF(H24<=0.8,"A",IF(H24<=0.95,"B","C")) -> A
A25: 24 | B25: 22411 | C25: JUMBO SHOPPER VINTAGE RED PAISLEY | D25: 1.95 | E25: 13462 | F25: 28344.94 | G25: =F25+G24 -> 1157135.9 | H25: =G25/$G$4871 -> 0.12123692 | I25: =IF(H25<=0.8,"A",IF(H25<=0.95,"B","C")) -> A
A26: 25 | B26: 82484 | C26: WOOD BLACK BOARD ANT WHITE FINISH | D26: 6.75 | E26: 4908 | F26: 28334.24 | G26: =F26+G25 -> 1185470.1 | H26: =G26/$G$4871 -> 0.1242056 | I26: =IF(H26<=0.8,"A",IF(H26<=0.95,"B","C")) -> A
A27: 26 | B27: 84347 | C27: ROTATING SILVER ANGELS T-LIGHT HLDR | D27: 2.55 | E27: 11034 | F27: 27763.95 | G27: =F27+G26 -> 1213234.1 | H27: =G27/$G$4871 -> 0.12711452 | I27: =IF(H27<=0.8,"A",IF(H27<=0.95,"B","C")) -> A
A28: 27 | B28: 22470 | C28: HEART OF WICKER LARGE | D28: 2.95 | E28: 8743 | F28: 26393.74 | G28: =F28+G27 -> 1239627.8 | H28: =G28/$G$4871 -> 0.12987988 | I28: =IF(H28<=0.8,"A",IF(H28<=0.95,"B","C")) -> A
A29: 28 | B29: 20914 | C29: SET/5 RED RETROSPOT LID GLASS BOWLS | D29: 2.95 | E29: 9221 | F29: 25962.78 | G29: =F29+G28 -> 1265590.6 | H29: =G29/$G$4871 -> 0.13260008 | I29: =IF(H29<=0.8,"A",IF(H29<=0.95,"B","C")) -> A
A30: 29 | B30: 22178 | C30: VICTORIAN GLASS HANGING T-LIGHT | D30: 1.25 | E30: 19798 | F30: 25923.64 | G30: =F30+G29 -> 1291514.2 | H30: =G30/$G$4871 -> 0.13531619 | I30: =IF(H30<=0.8,"A",IF(H30<=0.95,"B","C")) -> A
A31: 30 | B31: 21212 | C31: PACK OF 72 RETROSPOT CAKE CASES | D31: 0.55 | E31: 47098 | F31: 25731.18 | G31: =F31+G30 -> 1317245.4 | H31: =G31/$G$4871 -> 0.13801213 | I31: =IF(H31<=0.8,"A",IF(H31<=0.95,"B","C")) -> A
A32: 31 | B32: 22139 | C32: RETROSPOT TEA SET CERAMIC 11 PC | D32: 4.95 | E32: 5127 | F32: 25667.48 | G32: =F32+G31 -> 1342912.9 | H32: =G32/$G$4871 -> 0.14070139 | I32: =IF(H32<=0.8,"A",IF(H32<=0.95,"B","C")) -> A
A33: 32 | B33: 21181 | C33: PLEASE ONE PERSON METAL SIGN | D33: 2.1 | E33: 12360 | F33: 25051.97 | G33: =F33+G32 -> 1367964.9 | H33: =G33/$G$4871 -> 0.14332617 | I33: =IF(H33<=0.8,"A",IF(H33<=0.95,"B","C")) -> A
A34: 33 | B34: 22111 | C34: SCOTTIE DOG HOT WATER BOTTLE | D34: 4.95 | E34: 4868 | F34: 24807.97 | G34: =F34+G33 -> 1392772.8 | H34: =G34/$G$4871 -> 0.14592538 | I34: =IF(H34<=0.8,"A",IF(H34<=0.95,"B","C")) -> A
A35: 34 | B35: 21733 | C35: RED HANGING HEART T-LIGHT HOLDER | D35: 2.95 | E35: 8618 | F35: 24743.62 | G35: =F35+G34 -> 1417516.5 | H35: =G35/$G$4871 -> 0.14851785 | I35: =IF(H35<=0.8,"A",IF(H35<=0.95,"B","C")) -> A
... A44: 43 | B44: 21731 | C44: RED TOADSTOOL LED NIGHT LIGHT | D44: 1.65 | E44: 14058 | F44: 23578.7 | G44: =F44+G43 -> 1636437 | H44: =G44/$G$4871 -> 0.17145488 | I44: =IF(H44<=0.8,"A",IF(H44<=0.95,"B","C")) -> A
A45: 44 | B45: 15056BL | C45: EDWARDIAN PARASOL BLACK | D45: 5.95 | E45: 4712 | F45: 23452.75 | G45: =F45+G44 -> 1659889.8 | H45: =G45/$G$4871 -> 0.1739121 | I45: =IF(H45<=0.8,"A",IF(H45<=0.95,"B","C")) -> A
A46: 45 | B46: 21754 | C46: HOME BUILDING BLOCK WORD | D46: 5.95 | E46: 3816 | F46: 23366.34 | G46: =F46+G45 -> 1683256.1 | H46: =G46/$G$4871 -> 0.17636027 | I46: =IF(H46<=0.8,"A",IF(H46<=0.95,"B","C")) -> A
A47: 46 | B47: 48187 | C47: DOORMAT NEW ENGLAND | D47: 7.72 | E47: 3668 | F47: 23286.98 | G47: =F47+G46 -> 1706543.1 | H47: =G47/$G$4871 -> 0.17880012 | I47: =IF(H47<=0.8,"A",IF(H47<=0.95,"B","C")) -> A
A48: 47 | B48: 21523 | C48: DOORMAT FANCY FONT HOME SWEET HOME | D48: 7.95 | E48: 3458 | F48: 23037.65 | G48: =F48+G47 -> 1729580.7 | H48: =G48/$G$4871 -> 0.18121385 | I48: =IF(H48<=0.8,"A",IF(H48<=0.95,"B","C")) -> A
A49: 48 | B49: 21928 | C49: JUMBO BAG SCANDINAVIAN PAISLEY | D49: 1.95 | E49: 12042 | F49: 22939.03 | G49: =F49+G48 -> 1752519.8 | H49: =G49/$G$4871 -> 0.18361725 | I49: =IF(H49<=0.8,"A",IF(H49<=0.95,"B","C")) -> A
A50: 49 | B50: 22355 | C50: CHARLOTTE BAG SUKI DESIGN | D50: 0.85 | E50: 15945 | F50: 22667.23 | G50: =F50+G49 -> 1775187 | H50: =G50/$G$4871 -> 0.18599217 | I50: =IF(H50<=0.8,"A",IF(H50<=0.95,"B","C")) -> A
A51: 50 | B51: 21623 | C51: VINTAGE UNION JACK MEMOBOARD | D51: 9.95 | E51: 3062 | F51: 22521.14 | G51: =F51+G50 -> 1797708.1 | H51: =G51/$G$4871 -> 0.18835178 | I51: =IF(H51<=0.8,"A",IF(H51<=0.95,"B","C")) -> A
A52: 51 | B52: 22326 | C52: ROUND SNACK BOXES SET OF4 WOODLAND | D52: 2.95 | E52: 7726 | F52: 22136.25 | G52: =F52+G51 -> 1819844.4 | H52: =G52/$G$4871 -> 0.19067107 | I52: =IF(H52<=0.8,"A",IF(H52<=0.95,"B","C")) -> A
A53: 52 | B53: 20727 | C53: LUNCH BAG BLACK SKULL. | D53: 1.65 | E53: 12828 | F53: 22088.48 | G53: =F53+G52 -> 1841932.9 | H53: =G53/$G$4871 -> 0.19298535 | I53: =IF(H53<=0.8,"A",IF(H53<=0.95,"B","C")) -> A
A54: 53 | B54: 22138 | C54: BAKING SET 9 PIECE RETROSPOT | D54: 4.95 | E54: 4428 | F54: 21730.88 | G54: =F54+G53 -> 1863663.7 | H54: =G54/$G$4871 -> 0.19526217 | I54: =IF(H54<=0.8,"A",IF(H54<=0.95,"B","C")) -> A
A55: 54 | B55: 84029E | C55: RED WOOLLY HOTTIE WHITE HEART. | D55: 3.75 | E55: 5342 | F55: 21592.02 | G55: =F55+G54 -> 1885255.8 | H55: =G55/$G$4871 -> 0.19752443 | I55: =IF(H55<=0.8,"A",IF(H55<=0.95,"B","C")) -> A
A56: 55 | B56: 23298 | C56: SPOTTY BUNTING | D56: 4.95 | E56: 4233 | F56: 21574.09 | G56: =F56+G55 -> 1906829.8 | H56: =G56/$G$4871 -> 0.19978482 | I56: =IF(H56<=0.8,"A",IF(H56<=0.95,"B","C")) -> A
A57: 56 | B57: 22383 | C57: LUNCH BAG SUKI DESIGN | D57: 1.65 | E57: 12484 | F57: 21562.92 | G57: =F57+G56 -> 1928392.8 | H57: =G57/$G$4871 -> 0.20204404 | I57: =IF(H57<=0.8,"A",IF(H57<=0.95,"B","C")) -> A
A58: 57 | B58: 82494L | C58: WOODEN FRAME ANTIQUE WHITE | D58: 2.95 | E58: 7458 | F58: 21418.38 | G58: =F58+G57 -> 1949811.1 | H58: =G58/$G$4871 -> 0.20428811 | I58: =IF(H58<=0.8,"A",IF(H58<=0.95,"B","C")) -> A
A59: 58 | B59: 21915 | C59: RED HARMONICA IN BOX | D59: 1.25 | E59: 17756 | F59: 20903.02 | G59: =F59+G58 -> 1970714.2 | H59: =G59/$G$4871 -> 0.20647819 | I59: =IF(H59<=0.8,"A",IF(H59<=0.95,"B","C")) -> A
A60: 59 | B60: 23203 | C60: JUMBO BAG VINTAGE DOILY | D60: 2.08 | E60: 10081 | F60: 20725.65 | G60: =F60+G59 -> 1991439.8 | H60: =G60/$G$4871 -> 0.20864968 | I60: =IF(H60<=0.8,"A",IF(H60<=0.95,"B","C")) -> A
A61: 60 | B61: 71477 | C61: COLOUR GLASS. STAR T-LIGHT HOLDER | D61: 3.25 | E61: 6904 | F61: 20569.34 | G61: =F61+G60 -> 2012009.1 | H61: =G61/$G$4871 -> 0.2108048 | I61: =IF(H61<=0.8,"A",IF(H61<=0.95,"B","C")) -> A
A62: 61 | B62: 48185 | C62: DOORMAT FAIRY CAKE | D62: 7.95 | E62: 3070 | F62: 20563.96 | G62: =F62+G61 -> 2032573.1 | H62: =G62/$G$4871 -> 0.21295936 | I62: =IF(H62<=0.8,"A",IF(H62<=0.95,"B","C")) -> A
A63: 62 | B63: 20728 | C63: LUNCH BAG CARS BLUE | D63: 1.65 | E63: 11860 | F63: 20501.28 | G63: =F63+G62 -> 2053074.4 | H63: =G63/$G$4871 -> 0.21510734 | I63: =IF(H63<=0.8,"A",IF(H63<=0.95,"B","C")) -> A
A64: 63 | B64: 82482 | C64: WOODEN PICTURE FRAME WHITE FINISH | D64: 2.55 | E64: 8267 | F64: 20490.9 | G64: =F64+G63 -> 2073565.3 | H64: =G64/$G$4871 -> 0.21725424 | I64: =IF(H64<=0.8,"A",IF(H64<=0.95,"B","C")) -> A
A65: 64 | B65: 20713 | C65: JUMBO BAG OWLS | D65: 1.95 | E65: 10298 | F65: 20150.32 | G65: =F65+G64 -> 2093715.6 | H65: =G65/$G$4871 -> 0.21936546 | I65: =IF(H65<=0.8,"A",IF(H65<=0.95,"B","C")) -> A
A66: 65 | B66: 21175 | C66: GIN + TONIC DIET METAL SIGN | D66: 2.1 | E66: 9350 | F66: 20097.64 | G66: =F66+G65 -> 2113813.2 | H66: =G66/$G$4871 -> 0.22147115 | I66: =IF(H66<=0.8,"A",IF(H66<=0.95,"B","C")) -> A
A67: 66 | B67: 84997D | C67: PINK 3 PIECE MINI DOTS CUTLERY SET | D67: 3.75 | E67: 5316 | F67: 19898.6 | G67: =F67+G66 -> 2133711.9 | H67: =G67/$G$4871 -> 0.22355599 | I67: =IF(H67<=0.8,"A",IF(H67<=0.95,"B","C")) -> A
A68: 67 | B68: 84078A | C68: SET/4 WHITE RETRO STORAGE CUBES | D68: 39.95 | E68: 500 | F68: 19688.16 | G68: =F68+G67 -> 2153400 | H68: =G68/$G$4871 -> 0.22561879 | I68: =IF(H68<=0.8,"A",IF(H68<=0.95,"B","C")) -> A
A69: 68 | B69: 22083 | C69: PAPER CHAIN KIT RETROSPOT | D69: 2.95 | E69: 6634 | F69: 19616.14 | G69: =F69+G68 -> 2173016.1 | H69: =G69/$G$4871 -> 0.22767403 | I69: =IF(H69<=0.8,"A",IF(H69<=0.95,"B","C")) -> A
A70: 69 | B70: 85066 | C70: CREAM SWEETHEART MINI CHEST | D70: 12.75 | E70: 1530 | F70: 19110.39 | G70: =F70+G69 -> 2192126.5 | H70: =G70/$G$4871 -> 0.22967629 | I70: =IF(H70<=0.8,"A",IF(H70<=0.95,"B","C")) -> A
A71: 70 | B71: 22960 | C71: JAM MAKING SET WITH JARS | D71: 4.25 | E71: 4475 | F71: 19052.43 | G71: =F71+G70 -> 2211179 | H71: =G71/$G$4871 -> 0.23167248 | I71: =IF(H71<=0.8,"A",IF(H71<=0.95,"B","C")) -> A
A72: 71 | B72: 22720 | C72: SET OF 3 CAKE TINS PANTRY DESIGN | D72: 4.95 | E72: 3734 | F72: 19017.32 | G72: =F72+G71 -> 2230196.3 | H72: =G72/$G$4871 -> 0.23366498 | I72: =IF(H72<=0.8,"A",IF(H72<=0.95,"B","C")) -> A
A73: 72 | B73: 22629 | C73: SPACEBOY LUNCH BOX | D73: 1.95 | E73: 10412 | F73: 18995.3 | G73: =F73+G72 -> 2249191.6 | H73: =G73/$G$4871 -> 0.23565518 | I73: =IF(H73<=0.8,"A",IF(H73<=0.95,"B","C")) -> A
A74: 73 | B74: 82486 | C74: WOOD S/3 CABINET ANT WHITE FINISH | D74: 7.95 | E74: 2352 | F74: 18927.66 | G74: =F74+G73 -> 2268119.2 | H74: =G74/$G$4871 -> 0.2376383 | I74: =IF(H74<=0.8,"A",IF(H74<=0.95,"B","C")) -> A
A75: 74 | B75: 22699 | C75: ROSES REGENCY TEACUP AND SAUCER | D75: 2.95 | E75: 6431 | F75: 18856.35 | G75: =F75+G74 -> 2286975.6 | H75: =G75/$G$4871 -> 0.23961394 | I75: =IF(H75<=0.8,"A",IF(H75<=0.95,"B","C")) -> A
A76: 75 | B76: 21166 | C76: COOK WITH WINE METAL SIGN | D76: 1.95 | E76: 9734 | F76: 18681.25 | G76: =F76+G75 -> 2305656.9 | H76: =G76/$G$4871 -> 0.24157124 | I76: =IF(H76<=0.8,"A",IF(H76<=0.95,"B","C")) -> A
A77: 76 | B77: 21485 | C77: RETROSPOT HEART HOT WATER BOTTLE | D77: 4.95 | E77: 3814 | F77: 18620.04 | G77: =F77+G76 -> 2324276.9 | H77: =G77/$G$4871 -> 0.24352212 | I77: =IF(H77<=0.8,"A",IF(H77<=0.95,"B","C")) -> A
A78: 77 | B78: 20726 | C78: LUNCH BAG WOODLAND | D78: 1.65 | E78: 10616 | F78: 18606.24 | G78: =F78+G77 -> 2342883.1 | H78: =G78/$G$4871 -> 0.24547155 | I78: =IF(H78<=0.8,"A",IF(H78<=0.95,"B","C")) -> A
A79: 78 | B79: 20712 | C79: JUMBO BAG WOODLAND ANIMALS | D79: 2.08 | E79: 8750 | F79: 18564.9 | G79: =F79+G78 -> 2361448 | H79: =G79/$G$4871 -> 0.24741666 | I79: =IF(H79<=0.8,"A",IF(H79<=0.95,"B","C")) -> A
A80: 79 | B80: 23284 | C80: DOORMAT KEEP CALM AND COME IN | D80: 7.95 | E80: 2636 | F80: 18306.92 | G80: =F80+G79 -> 2379755 | H80: =G80/$G$4871 -> 0.24933474 | I80: =IF(H80<=0.8,"A",IF(H80<=0.95,"B","C")) -> A
... A86: 85 | B86: 22379 | C86: RECYCLING BAG RETROSPOT | D86: 2.1 | E86: 7892 | F86: 17340.37 | G86: =F86+G85 -> 2486430.6 | H86: =G86/$G$4871 -> 0.2605115 | I86: =IF(H86<=0.8,"A",IF(H86<=0.95,"B","C")) -> A
A87: 86 | B87: 84997B | C87: RED 3 PIECE MINI DOTS CUTLERY SET | D87: 3.75 | E87: 4584 | F87: 17088.24 | G87: =F87+G86 -> 2503518.9 | H87: =G87/$G$4871 -> 0.26230189 | I87: =IF(H87<=0.8,"A",IF(H87<=0.95,"B","C")) -> A
A88: 87 | B88: 22384 | C88: LUNCH BAG PINK POLKADOT | D88: 1.65 | E88: 10396 | F88: 17052.64 | G88: =F88+G87 -> 2520571.5 | H88: =G88/$G$4871 -> 0.26408855 | I88: =IF(H88<=0.8,"A",IF(H88<=0.95,"B","C")) -> A
A89: 88 | B89: 22382 | C89: LUNCH BAG SPACEBOY DESIGN | D89: 1.65 | E89: 10134 | F89: 17052.48 | G89: =F89+G88 -> 2537624 | H89: =G89/$G$4871 -> 0.26587519 | I89: =IF(H89<=0.8,"A",IF(H89<=0.95,"B","C")) -> A
A90: 89 | B90: 22666 | C90: RECIPE BOX PANTRY YELLOW DESIGN | D90: 2.95 | E90: 5306 | F90: 16717.06 | G90: =F90+G89 -> 2554341 | H90: =G90/$G$4871 -> 0.26762669 | I90: =IF(H90<=0.8,"A",IF(H90<=0.95,"B","C")) -> A
A91: 90 | B91: 22630 | C91: DOLLY GIRL LUNCH BOX | D91: 1.95 | E91: 8946 | F91: 16558.34 | G91: =F91+G90 -> 2570899.4 | H91: =G91/$G$4871 -> 0.26936157 | I91: =IF(H91<=0.8,"A",IF(H91<=0.95,"B","C")) -> A
A92: 91 | B92: 22726 | C92: ALARM CLOCK BAKELIKE GREEN | D92: 3.75 | E92: 3832 | F92: 16293.41 | G92: =F92+G91 -> 2587192.8 | H92: =G92/$G$4871 -> 0.27106868 | I92: =IF(H92<=0.8,"A",IF(H92<=0.95,"B","C")) -> A
A93: 92 | B93: 84997C | C93: BLUE 3 PIECE MINI DOTS CUTLERY SET | D93: 3.75 | E93: 4366 | F93: 16259.59 | G93: =F93+G92 -> 2603452.4 | H93: =G93/$G$4871 -> 0.27277225 | I93: =IF(H93<=0.8,"A",IF(H93<=0.95,"B","C")) -> A
A94: 93 | B94: 15036 | C94: ASSORTED COLOURS SILK FAN | D94: 0.83 | E94: 21716 | F94: 16197.56 | G94: =F94+G93 -> 2619649.9 | H94: =G94/$G$4871 -> 0.27446932 | I94: =IF(H94<=0.8,"A",IF(H94<=0.95,"B","C")) -> A
A95: 94 | B95: 22385 | C95: JUMBO BAG SPACEBOY DESIGN | D95: 1.95 | E95: 8326 | F95: 15875.07 | G95: =F95+G94 -> 2635525 | H95: =G95/$G$4871 -> 0.27613261 | I95: =IF(H95<=0.8,"A",IF(H95<=0.95,"B","C")) -> A
A96: 95 | B96: 22077 | C96: 6 RIBBONS RUSTIC CHARM | D96: 1.65 | E96: 8600 | F96: 15726.33 | G96: =F96+G95 -> 2651251.3 | H96: =G96/$G$4871 -> 0.2777803 | I96: =IF(H96<=0.8,"A",IF(H96<=0.95,"B","C")) -> A
A97: 96 | B97: 85152 | C97: HAND OVER THE CHOCOLATE SIGN | D97: 2.1 | E97: 8160 | F97: 15694.99 | G97: =F97+G96 -> 2666946.3 | H97: =G97/$G$4871 -> 0.27942472 | I97: =IF(H97<=0.8,"A",IF(H97<=0.95,"B","C")) -> A
A98: 97 | B98: 22865 | C98: HAND WARMER OWL DESIGN | D98: 2.1 | E98: 7252 | F98: 15672.32 | G98: =F98+G97 -> 2682618.6 | H98: =G98/$G$4871 -> 0.28106676 | I98: =IF(H98<=0.8,"A",IF(H98<=0.95,"B","C")) -> A
A99: 98 | B99: 21479 | C99: WHITE SKULL HOT WATER BOTTLE | D99: 3.75 | E99: 3116 | F99: 15566.65 | G99: =F99+G98 -> 2698185.3 | H99: =G99/$G$4871 -> 0.28269773 | I99: =IF(H99<=0.8,"A",IF(H99<=0.95,"B","C")) -> A
A100: 99 | B100: 48184 | C100: DOORMAT ENGLISH ROSE | D100: 7.95 | E100: 2356 | F100: 15554.44 | G100: =F100+G99 -> 2713739.7 | H100: =G100/$G$4871 -> 0.28432742 | I100: =IF(H100<=0.8,"A",IF(H100<=0.95,"B","C")) -> A
A101: 100 | B101: 23245 | C101: SET OF 3 REGENCY CAKE TINS | D101: 4.95 | E101: 3166 | F101: 15531.03 | G101: =F101+G100 -> 2729270.8 | H101: =G101/$G$4871 -> 0.28595466 | I101: =IF(H101<=0.8,"A",IF(H101<=0.95,"B","C")) -> A
A102: 101 | B102: 85014B | C102: RED RETROSPOT UMBRELLA | D102: 5.95 | E102: 3076 | F102: 15376.39 | G102: =F102+G101 -> 2744647.2 | H102: =G102/$G$4871 -> 0.28756569 | I102: =IF(H102<=0.8,"A",IF(H102<=0.95,"B","C")) -> A
A103: 102 | B103: 22697 | C103: GREEN REGENCY TEACUP AND SAUCER | D103: 2.95 | E103: 4874 | F103: 15151.32 | G103: =F103+G102 -> 2759798.5 | H103: =G103/$G$4871 -> 0.28915314 | I103: =IF(H103<=0.8,"A",IF(H103<=0.95,"B","C")) -> A
A104: 103 | B104: 22501 | C104: PICNIC BASKET WICKER LARGE | D104: 9.95 | E104: 1298 | F104: 15095.06 | G104: =F104+G103 -> 2774893.5 | H104: =G104/$G$4871 -> 0.2907347 | I104: =IF(H104<=0.8,"A",IF(H104<=0.95,"B","C")) -> A
A105: 104 | B105: 20679 | C105: EDWARDIAN PARASOL RED | D105: 5.95 | E105: 3072 | F105: 14992.64 | G105: =F105+G104 -> 2789886.2 | H105: =G105/$G$4871 -> 0.29230553 | I105: =IF(H105<=0.8,"A",IF(H105<=0.95,"B","C")) -> A
A106: 105 | B106: 21217 | C106: RED RETROSPOT ROUND CAKE TINS | D106: 9.95 | E106: 1439 | F106: 14761.27 | G106: =F106+G105 -> 2804647.5 | H106: =G106/$G$4871 -> 0.29385212 | I106: =IF(H106<=0.8,"A",IF(H106<=0.95,"B","C")) -> A
A107: 106 | B107: 84029G | C107: KNITTED UNION FLAG HOT WATER BOTTLE | D107: 3.75 | E107: 3412 | F107: 14753.39 | G107: =F107+G106 -> 2819400.8 | H107: =G107/$G$4871 -> 0.29539788 | I107: =IF(H107<=0.8,"A",IF(H107<=0.95,"B","C")) -> A
A108: 107 | B108: 23199 | C108: JUMBO BAG APPLES | D108: 2.08 | E108: 7149 | F108: 14680.84 | G108: =F108+G107 -> 2834081.7 | H108: =G108/$G$4871 -> 0.29693604 | I108: =IF(H108<=0.8,"A",IF(H108<=0.95,"B","C")) -> A
A109: 108 | B109: 22659 | C109: LUNCH BOX I LOVE LONDON | D109: 1.95 | E109: 7910 | F109: 14677.96 | G109: =F109+G108 -> 2848759.6 | H109: =G109/$G$4871 -> 0.2984739 | I109: =IF(H109<=0.8,"A",IF(H109<=0.95,"B","C")) -> A
A110: 109 | B110: 22158 | C110: 3 HEARTS HANGING DECORATION RUSTIC | D110: 2.95 | E110: 4516 | F110: 14668.46 | G110: =F110+G109 -> 2863428.1 | H110: =G110/$G$4871 -> 0.30001076 | I110: =IF(H110<=0.8,"A",IF(H110<=0.95,"B","C")) -> A
A111: 110 | B111: 47590B | C111: PINK HAPPY BIRTHDAY BUNTING | D111: 5.45 | E111: 2860 | F111: 14632.88 | G111: =F111+G110 -> 2878061 | H111: =G111/$G$4871 -> 0.30154389 | I111: =IF(H111<=0.8,"A",IF(H111<=0.95,"B","C")) -> A
A112: 111 | B112: 22622 | C112: BOX OF VINTAGE ALPHABET BLOCKS | D112: 9.95 | E112: 1444 | F112: 14461.3 | G112: =F112+G111 -> 2892522.3 | H112: =G112/$G$4871 -> 0.30305905 | I112: =IF(H112<=0.8,"A",IF(H112<=0.95,"B","C")) -> A
A113: 112 | B113: 23355 | C113: HOT WATER BOTTLE KEEP CALM | D113: 4.95 | E113: 2902 | F113: 14341.78 | G113: =F113+G112 -> 2906864.1 | H113: =G113/$G$4871 -> 0.30456169 | I113: =IF(H113<=0.8,"A",IF(H113<=0.95,"B","C")) -> A
...

Sheet SUMMARY
A1: PRODUCT | B1: ANNUAL_DEMAND | C1: BEST_FORECAST_DEMAND | D1: BEST_MAD | E1: EOQ | F1: ORDER_PER_YEAR | G1: SAFETY_STOCK | H1: REORDER_POINT
A2: ='ABC ANALYSIS'!K10 -> REGENCY CAKESTAND 3 TIER | B2: ='ABC ANALYSIS'!M10 -> 12894 | C2: EXP.SMOOTHING ALPHA 0.1 | D2: 57.7 | E2: ='ABC ANALYSIS'!O10 -> 711.08864 | F2: =B2/E2 -> 18.13276 | G2: ='ABC ANALYSIS'!S10 -> 416.14058 | H2: ='ABC ANALYSIS'!T10 -> 904.85212
A3: ='ABC ANALYSIS'!K11 -> WHITE HANGING HEART T-LIGHT HOLDER | B3: ='ABC ANALYSIS'!M11 -> 45480 | C3: EXP.SMOOTHING ALPHA 0.1 | D3: 292.3 | E3: ='ABC ANALYSIS'!O11 -> 2776.414 | F3: =B3/E3 -> 16.380842 | G3: ='ABC ANALYSIS'!S11 -> 1158.4479 | H3: ='ABC ANALYSIS'!T11 -> 2859.5825
A4: ='ABC ANALYSIS'!K12 -> JUMBO BAG RED RETROSPOT | B4: ='ABC ANALYSIS'!M12 -> 48012 | C4: EXP.SMOOTHING ALPHA 0.1 | D4: 481.9 | E4: ='ABC ANALYSIS'!O12 -> 3508.6706 | F4: =B4/E4 -> 13.683815 | G4: ='ABC ANALYSIS'!S12 -> 1105.9571 | H4: ='ABC ANALYSIS'!T12 -> 2920.8417
A5: ='ABC ANALYSIS'!K13 -> PARTY BUNTING | B5: ='ABC ANALYSIS'!M13 -> 14008 | C5: MOVING AVERAGE 3 WEEKS | D5: 88.5 | E5: ='ABC ANALYSIS'!O13 -> 1189.5165 | F5: =B5/E5 -> 11.776213 | G5: ='ABC ANALYSIS'!S13 -> 561.8699 | H5: ='ABC ANALYSIS'!T13 -> 1098.4468
A6: ='ABC ANALYSIS'!K14 -> ASSORTED COLOUR BIRD ORNAMENT | B6: ='ABC ANALYSIS'!M14 -> 39922 | C6: EXP.SMOOTHING ALPHA 0.1 | D6: 235.7 | E6: ='ABC ANALYSIS'!O14 -> 3436.7488 | F6: =B6/E6 -> 11.616211 | G6: ='ABC ANALYSIS'!S14 -> 1621.2176 | H6: ='ABC ANALYSIS'!T14 -> 3104.833
A7: ='ABC ANALYSIS'!K15 -> PAPER CHAIN KIT 50'S CHRISTMAS | B7: ='ABC ANALYSIS'!M15 -> 17330 | C7: EXP.SMOOTHING ALPHA 0.5 | D7: 301.6 | E7: ='ABC ANALYSIS'!O15 -> 1713.8518 | F7: =B7/E7 -> 10.111726 | G7: ='ABC ANALYSIS'!S15 -> 1219.9292 | H7: ='ABC ANALYSIS'!T15 -> 1818.1792
A8: ='ABC ANALYSIS'!K16 -> CHILLI LIGHTS | B8: ='ABC ANALYSIS'!M16 -> 7906 | C8: EXP.SMOOTHING ALPHA 0.1 | D8: 167.7 | E8: ='ABC ANALYSIS'!O16 -> 893.63631 | F8: =B8/E8 -> 8.8469995 | G8: ='ABC ANALYSIS'!S16 -> 444.72134 | H8: ='ABC ANALYSIS'!T16 -> 741.22134
A9: ='ABC ANALYSIS'!K17 -> SMALL POPCORN HOLDER | B9: ='ABC ANALYSIS'!M17 -> 44152 | C9: MOVING AVERAGE 3 WEEKS | D9: 555.7 | E9: ='ABC ANALYSIS'!O17 -> 5096.2501 | F9: =B9/E9 -> 8.6636251 | G9: ='ABC ANALYSIS'!S17 -> 2107.1828 | H9: ='ABC ANALYSIS'!T17 -> 3706.6059
A10: ='ABC ANALYSIS'!K18 -> JUMBO BAG PINK POLKADOT | B10: ='ABC ANALYSIS'!M18 -> 19506 | C10: EXP.SMOOTHING ALPHA 0.1 | D10: 262.6 | E10: ='ABC ANALYSIS'!O18 -> 2236.412 | F10: =B10/E10 -> 8.7220067 | G10: ='ABC ANALYSIS'!S18 -> 593.39582 | H10: ='ABC ANALYSIS'!T18 -> 1341.6458
A11: ='ABC ANALYSIS'!K19 -> LUNCH BAG RED RETROSPOT | B11: ='ABC ANALYSIS'!M19 -> 19968 | C11: EXP.SMOOTHING ALPHA 0.1 | D11: 114.9 | E11: ='ABC ANALYSIS'!O19 -> 2459.8596 | F11: =B11/E11 -> 8.1175366 | G11: ='ABC ANALYSIS'!S19 -> 410.33065 | H11: ='ABC ANALYSIS'!T19 -> 1167.3499
A14: ASSUMPTIONS: | C14: KEY_RESULTS:
A15: ORDER COST=50 GBP PER ORDER | C15: 1. ABC:1052 OUT OF 4870 PRODUCTS(22%)MAKE 80% OF SALES VALUE.THE TOP 10 PRODUCTS ARE ALL CLASS A.
A16: HOLDING COST=20%OF UNIT PRICE PER YEAR | C16: 2. FORECAST: EXPONENTIAL SMOOTHING(ALPHA 0.1) WAS THE BEST FOR 7 OUT OF 10 PRODUCTS, 3-WEEK MOVING AVERAGE FOR 2 PRODUCTS(PARTY BUNTING,POPCORN HOLDER) AND ALPHA 0.5 FOR PAPER CHAIN KIT(SEASONAL).
A17: LEAD TIME=2 WEEKS | C17: 3. FORECAST EROR(MAD) IS ROUGHLY 26% TO 57% OF AVERAGE WEEKLY SALES.
A18: SERVICE LEVEL=95% | C18: 4. EOQ RANGES FROM ABOUT 711 UNITS (REGENCY CAKE STAND) TO ABOUT 5096(SMALL POPCORN HOLDER),OR 8 TO 18 ORDERS PER YEAR.
A19: FORECAST ACCURACY MEASURED BY MAD ON THE LAST 12 WEEKS | C19: 5. SAFETY STOCK RANGES FROM 410 TO 2107 UNITS,AND REORDER POINTS FROM 741 TO 3707 UNITS.
A21: DATA: | C21: LIMITATIONS:
A22: ONLINE RETAIL II (DEC2009 TO NOV 2011),CLEANED | C22: 1.ORDER COST,HOLDING COST,LEAD TIME AND SERVICE LEVEL ARE ASSUMED, NOT TAKEN FROM THE DATA.
C23: 2. DEMAND IS GROSS SALES.PARTIAL RETURNS WERE NOT SUBRACTED.
C24: 3. PRICES AND SELLING PRICES,NOT COSTS.
C25: 4.FORECAST WERE TESTED ON ONLY THE LAST 12 WEEKS.
C26: 5. SOME PRODUCTS HAVE LUMPY OR SEASONAL DEMAND(PAPER CHAIN KIT HAS 22 ZERO WEEKS),SO ERROR ARE LARGE.
C27: 6. EOQ AND SAFETY STOCK WERE CALCULATED FOR THE TOP 10 PRODUCTS.
